{
  "generatedAt": "2026-04-29T22:34:35.053Z",
  "policy": {
    "mode": "public-list-only",
    "policyVersion": "1.2.0",
    "sourceCount": 9,
    "recentWindowHours": 336
  },
  "compliance": [
    {
      "source": "뽐뿌",
      "status": "ok",
      "collected": 18
    },
    {
      "source": "해외뽐뿌",
      "status": "ok",
      "collected": 32
    },
    {
      "source": "알리뽐뿌",
      "status": "ok",
      "collected": 16
    },
    {
      "source": "FM코리아",
      "status": "error",
      "message": "HTTP 430"
    },
    {
      "source": "개드립",
      "status": "ok",
      "collected": 3
    },
    {
      "source": "루리웹",
      "status": "ok",
      "collected": 16
    },
    {
      "source": "딜바다 국내",
      "status": "ok",
      "collected": 29
    },
    {
      "source": "딜바다 해외",
      "status": "ok",
      "collected": 30
    },
    {
      "source": "쿨엔조이",
      "status": "error",
      "message": "fetch failed"
    }
  ],
  "deals": [
    {
      "id": 1,
      "title": "[뽐뿌] DOOMBLADE",
      "productName": "DOOMBLADE",
      "category": "festa",
      "source": "뽐뿌",
      "platform": "",
      "price": 0,
      "priceText": "",
      "shipping": "무료",
      "discount": 0,
      "createdAt": "2026-04-29T22:29:18.000Z",
      "deadlineAt": "",
      "deadlineText": "",
      "statusText": "",
      "expiresAt": "",
      "eventTags": [
        "할인페스타"
      ],
      "sourceCategory": "",
      "summary": "DOOMBLADE 특가입니다. 무료.",
      "summaryPoints": [
        "배송: 무료"
      ],
      "originalUrl": "https://www.ppomppu.co.kr/zboard/view.php?id=ppomppu&page=1&divpage=111&no=700427",
      "purchaseUrl": "https://s.ppomppu.co.kr/?idno=ppomppu_700427&target=aHR0cHM6Ly9zdG9yZS5lcGljZ2FtZXMuY29tL2tvL3AvZG9vbWJsYWRlLWFmZGY5YQ==&encode=on",
      "url": "https://www.ppomppu.co.kr/zboard/view.php?id=ppomppu&page=1&divpage=111&no=700427"
    },
    {
      "id": 2,
      "title": "[뽐뿌] 베스킨라빈스 피카츄 케이크",
      "productName": "베스킨라빈스 피카츄 케이크",
      "category": "dessert",
      "source": "뽐뿌",
      "platform": "",
      "price": 20600,
      "priceText": "20,600원",
      "shipping": "무료",
      "discount": 0,
      "createdAt": "2026-04-29T22:22:59.000Z",
      "deadlineAt": "",
      "deadlineText": "",
      "statusText": "",
      "expiresAt": "",
      "eventTags": [
        "식품"
      ],
      "sourceCategory": "",
      "summary": "베스킨라빈스 피카츄 케이크 특가입니다. 20,600원, 무료.",
      "summaryPoints": [
        "가격: 20,600원",
        "배송: 무료"
      ],
      "originalUrl": "https://www.ppomppu.co.kr/zboard/view.php?id=ppomppu&page=1&divpage=111&no=700426",
      "purchaseUrl": "https://s.ppomppu.co.kr/?idno=ppomppu_700426&target=aHR0cHM6Ly9ra28udG8vazhreVBFV1BrOQ==&encode=on",
      "url": "https://www.ppomppu.co.kr/zboard/view.php?id=ppomppu&page=1&divpage=111&no=700426"
    },
    {
      "id": 3,
      "title": "[뽐뿌] 다크 초콜릿 브라우니 5개들이 2세트",
      "productName": "다크 초콜릿 브라우니 5개들이 2세트",
      "category": "festa",
      "source": "뽐뿌",
      "platform": "",
      "price": 34800,
      "priceText": "34,800원",
      "shipping": "무료",
      "discount": 0,
      "createdAt": "2026-04-29T21:56:50.000Z",
      "deadlineAt": "",
      "deadlineText": "",
      "statusText": "",
      "expiresAt": "",
      "eventTags": [
        "할인페스타"
      ],
      "sourceCategory": "",
      "summary": "다크 초콜릿 브라우니 5개들이 2세트 특가입니다. 34,800원, 무료.",
      "summaryPoints": [
        "가격: 34,800원",
        "배송: 무료"
      ],
      "originalUrl": "https://www.ppomppu.co.kr/zboard/view.php?id=ppomppu&page=1&divpage=111&no=700425",
      "purchaseUrl": "https://s.ppomppu.co.kr/?idno=ppomppu_700425&target=aHR0cHM6Ly9nb2RpdmFrb3JlYS5teXNvaG8uY29tLw==&encode=on",
      "url": "https://www.ppomppu.co.kr/zboard/view.php?id=ppomppu&page=1&divpage=111&no=700425"
    },
    {
      "id": 4,
      "title": "[뽐뿌] 그린핑거 프레쉬 선쿠션 2개세트",
      "productName": "그린핑거 프레쉬 선쿠션 2개세트",
      "category": "festa",
      "source": "뽐뿌",
      "platform": "",
      "price": 19700,
      "priceText": "19700원",
      "shipping": "",
      "discount": 0,
      "createdAt": "2026-04-29T21:26:12.000Z",
      "deadlineAt": "",
      "deadlineText": "",
      "statusText": "",
      "expiresAt": "",
      "eventTags": [
        "할인페스타"
      ],
      "sourceCategory": "",
      "summary": "그린핑거 프레쉬 선쿠션 2개세트 특가입니다. 19700원.",
      "summaryPoints": [
        "가격: 19700원"
      ],
      "originalUrl": "https://www.ppomppu.co.kr/zboard/view.php?id=ppomppu&page=1&divpage=111&no=700423",
      "purchaseUrl": "https://s.ppomppu.co.kr/?idno=ppomppu_700423&target=aHR0cHM6Ly93d3cuZG9vdGFvbi5jb20vbS9wcm9kdWN0Lmh0bWw/YnJhbmR1aWQ9MTMzMDYzMDA0JnNlYXJjaD0meGNvZGU9MDEzJm1jb2RlPTAwMSZzY29kZT0mR2ZEVD1aMlozVlElM0QlM0Qjbm9uZQ==&encode=on",
      "url": "https://www.ppomppu.co.kr/zboard/view.php?id=ppomppu&page=1&divpage=111&no=700423"
    },
    {
      "id": 5,
      "title": "[지마켓] 레쓰비 마일드 30캔+모카라떼 30캔 (17,900원/무료)",
      "productName": "레쓰비 마일드 30캔+모카라떼 30캔 (17,900원/무료)",
      "category": "festa",
      "source": "루리웹",
      "platform": "지마켓",
      "price": 17900,
      "priceText": "17,900원",
      "shipping": "무료",
      "discount": 0,
      "createdAt": "2026-04-29T21:15:00.000Z",
      "deadlineAt": "",
      "deadlineText": "",
      "statusText": "",
      "expiresAt": "",
      "eventTags": [
        "할인페스타"
      ],
      "sourceCategory": "음식",
      "summary": "레쓰비 마일드 30캔+모카라떼 30캔 (17,900원/무료) 특가입니다. 지마켓 기준 17,900원, 무료.",
      "summaryPoints": [
        "플랫폼: 지마켓",
        "가격: 17,900원",
        "배송: 무료"
      ],
      "originalUrl": "https://bbs.ruliweb.com/market/board/1020/read/103780?",
      "purchaseUrl": "https://web.ruliweb.com/link.php?ol=https%3A%2F%2Fm.gmarket.co.kr%2Fvi%2Fproduct%2F4641573204&bbs=1020",
      "url": "https://bbs.ruliweb.com/market/board/1020/read/103780?"
    },
    {
      "id": 6,
      "title": "[네이버] 참도깨비 의정부식 1960 부대찌개 700g 2개 네이버 멤버쉽",
      "productName": "참도깨비 의정부식 1960 부대찌개 700g 2개 네이버 멤버쉽",
      "category": "festa",
      "source": "뽐뿌",
      "platform": "네이버",
      "price": 7900,
      "priceText": "7,900원",
      "shipping": "무료",
      "discount": 0,
      "createdAt": "2026-04-29T19:24:10.000Z",
      "deadlineAt": "",
      "deadlineText": "",
      "statusText": "",
      "expiresAt": "",
      "eventTags": [
        "할인페스타"
      ],
      "sourceCategory": "",
      "summary": "참도깨비 의정부식 1960 부대찌개 700g 2개 네이버 멤버쉽 특가입니다. 네이버 기준 7,900원, 무료.",
      "summaryPoints": [
        "플랫폼: 네이버",
        "가격: 7,900원",
        "배송: 무료"
      ],
      "originalUrl": "https://www.ppomppu.co.kr/zboard/view.php?id=ppomppu&page=1&divpage=111&no=700422",
      "purchaseUrl": "https://s.ppomppu.co.kr/?idno=ppomppu_700422&target=aHR0cHM6Ly9uYXZlci5tZS9HUUdtb2RicQ==&encode=on",
      "url": "https://www.ppomppu.co.kr/zboard/view.php?id=ppomppu&page=1&divpage=111&no=700422"
    },
    {
      "id": 7,
      "title": "[11번가] 하우스 꿀수박 6kg",
      "productName": "하우스 꿀수박 6kg",
      "category": "festa",
      "source": "뽐뿌",
      "platform": "11번가",
      "price": 17910,
      "priceText": "17,910원",
      "shipping": "무배",
      "discount": 0,
      "createdAt": "2026-04-29T17:38:54.000Z",
      "deadlineAt": "",
      "deadlineText": "",
      "statusText": "",
      "expiresAt": "",
      "eventTags": [
        "할인페스타"
      ],
      "sourceCategory": "",
      "summary": "하우스 꿀수박 6kg 특가입니다. 11번가 기준 17,910원, 무배.",
      "summaryPoints": [
        "플랫폼: 11번가",
        "가격: 17,910원",
        "배송: 무배"
      ],
      "originalUrl": "https://www.ppomppu.co.kr/zboard/view.php?id=ppomppu&page=1&divpage=111&no=700421",
      "purchaseUrl": "https://s.ppomppu.co.kr/?idno=ppomppu_700421&target=aHR0cDovL3d3dy4xMXN0LmNvLmtyL3Byb2R1Y3RzLzgyNTc1NjY0MjYvc2hhcmU=&encode=on",
      "url": "https://www.ppomppu.co.kr/zboard/view.php?id=ppomppu&page=1&divpage=111&no=700421"
    },
    {
      "id": 8,
      "title": "[옥션] 1+1 남자7부 아이스쿨반바지 2장",
      "productName": "1+1 남자7부 아이스쿨반바지 2장",
      "category": "festa",
      "source": "뽐뿌",
      "platform": "옥션",
      "price": 0,
      "priceText": "",
      "shipping": "무배",
      "discount": 0,
      "createdAt": "2026-04-29T17:35:35.000Z",
      "deadlineAt": "",
      "deadlineText": "",
      "statusText": "",
      "expiresAt": "",
      "eventTags": [
        "할인페스타"
      ],
      "sourceCategory": "",
      "summary": "1+1 남자7부 아이스쿨반바지 2장 특가입니다. 옥션 기준 무배.",
      "summaryPoints": [
        "플랫폼: 옥션",
        "배송: 무배"
      ],
      "originalUrl": "https://www.ppomppu.co.kr/zboard/view.php?id=ppomppu&page=1&divpage=111&no=700420",
      "purchaseUrl": "https://s.ppomppu.co.kr/?idno=ppomppu_700420&target=aHR0cHM6Ly9pdGVtLmdtYXJrZXQuY28ua3IvSXRlbT9nb29kc2NvZGU9NDcyNjAwNjA5MQ==&encode=on",
      "url": "https://www.ppomppu.co.kr/zboard/view.php?id=ppomppu&page=1&divpage=111&no=700420"
    },
    {
      "id": 9,
      "title": "[뽐뿌] 온더고 고퀄 집밥세트 12개+직장인 추천 5종 총 17개",
      "productName": "온더고 고퀄 집밥세트 12개+직장인 추천 5종 총 17개",
      "category": "festa",
      "source": "뽐뿌",
      "platform": "",
      "price": 46592,
      "priceText": "46,592원",
      "shipping": "무료",
      "discount": 0,
      "createdAt": "2026-04-29T17:00:07.000Z",
      "deadlineAt": "",
      "deadlineText": "",
      "statusText": "",
      "expiresAt": "",
      "eventTags": [
        "할인페스타"
      ],
      "sourceCategory": "",
      "summary": "온더고 고퀄 집밥세트 12개+직장인 추천 5종 총 17개 특가입니다. 46,592원, 무료.",
      "summaryPoints": [
        "가격: 46,592원",
        "배송: 무료"
      ],
      "originalUrl": "https://www.ppomppu.co.kr/zboard/view.php?id=ppomppu&page=1&divpage=111&no=700419",
      "purchaseUrl": "https://s.ppomppu.co.kr/?idno=ppomppu_700419&target=aHR0cHM6Ly9tYWxsLm91cmhvbWUuY28ua3IvbWFsbC9wcm9kdWN0L2RldGFpbC5kbz9nb29kc19pZD1TMDAwMDAwMDExOTg2&encode=on",
      "url": "https://www.ppomppu.co.kr/zboard/view.php?id=ppomppu&page=1&divpage=111&no=700419"
    },
    {
      "id": 10,
      "title": "[뽐뿌] 온더고X한화이글스] 이글스 떡볶이 2종(불패/마라) X 12팩",
      "productName": "온더고X한화이글스] 이글스 떡볶이 2종(불패/마라) X 12팩",
      "category": "festa",
      "source": "뽐뿌",
      "platform": "",
      "price": 21756,
      "priceText": "21756원",
      "shipping": "무료",
      "discount": 0,
      "createdAt": "2026-04-29T16:36:32.000Z",
      "deadlineAt": "",
      "deadlineText": "",
      "statusText": "",
      "expiresAt": "",
      "eventTags": [
        "할인페스타"
      ],
      "sourceCategory": "",
      "summary": "온더고X한화이글스] 이글스 떡볶이 2종(불패/마라) X 12팩 특가입니다. 21756원, 무료.",
      "summaryPoints": [
        "가격: 21756원",
        "배송: 무료"
      ],
      "originalUrl": "https://www.ppomppu.co.kr/zboard/view.php?id=ppomppu&page=1&divpage=111&no=700418",
      "purchaseUrl": "https://s.ppomppu.co.kr/?idno=ppomppu_700418&target=aHR0cHM6Ly9tYWxsLm91cmhvbWUuY28ua3IvbWFsbC9wcm9kdWN0L2RldGFpbC5kbz9nb29kc19pZD1TMDAwMDAwMDExMzgyJmRhaWx5X3luPU4=&encode=on",
      "url": "https://www.ppomppu.co.kr/zboard/view.php?id=ppomppu&page=1&divpage=111&no=700418"
    },
    {
      "id": 11,
      "title": "[옥션] 남녀공용 커플 바스락 배삭 반팔상의",
      "productName": "남녀공용 커플 바스락 배삭 반팔상의",
      "category": "festa",
      "source": "뽐뿌",
      "platform": "옥션",
      "price": 0,
      "priceText": "",
      "shipping": "무배",
      "discount": 0,
      "createdAt": "2026-04-29T16:30:17.000Z",
      "deadlineAt": "",
      "deadlineText": "",
      "statusText": "",
      "expiresAt": "",
      "eventTags": [
        "할인페스타"
      ],
      "sourceCategory": "",
      "summary": "남녀공용 커플 바스락 배삭 반팔상의 특가입니다. 옥션 기준 무배.",
      "summaryPoints": [
        "플랫폼: 옥션",
        "배송: 무배"
      ],
      "originalUrl": "https://www.ppomppu.co.kr/zboard/view.php?id=ppomppu&page=1&divpage=111&no=700417",
      "purchaseUrl": "https://s.ppomppu.co.kr/?idno=ppomppu_700417&target=aHR0cHM6Ly9pdGVtcGFnZTMuYXVjdGlvbi5jby5rci9EZXRhaWxWaWV3LmFzcHg/SXRlbU5vPUY1NDk2MDgyMjMmZnJtMz1WMg==&encode=on",
      "url": "https://www.ppomppu.co.kr/zboard/view.php?id=ppomppu&page=1&divpage=111&no=700417"
    },
    {
      "id": 12,
      "title": "[뽐뿌] 100gb 5mbps 4개월 알뜰무제한요금제",
      "productName": "100gb 5mbps 4개월 알뜰무제한요금제",
      "category": "festa",
      "source": "뽐뿌",
      "platform": "",
      "price": 2900,
      "priceText": "2,900원",
      "shipping": "무료",
      "discount": 0,
      "createdAt": "2026-04-29T16:30:01.000Z",
      "deadlineAt": "",
      "deadlineText": "",
      "statusText": "",
      "expiresAt": "",
      "eventTags": [
        "할인페스타"
      ],
      "sourceCategory": "",
      "summary": "100gb 5mbps 4개월 알뜰무제한요금제 특가입니다. 2,900원, 무료.",
      "summaryPoints": [
        "가격: 2,900원",
        "배송: 무료"
      ],
      "originalUrl": "https://www.ppomppu.co.kr/zboard/view.php?id=ppomppu&page=1&divpage=111&no=700416",
      "purchaseUrl": "https://s.ppomppu.co.kr/?idno=ppomppu_700416&target=aHR0cHM6Ly93d3cucGluZGlyZWN0c2hvcC5jb20vZGVhbC12aWV3L2V2ZW50L2E1ZmU5ZTBlLTZkZjYtNDA1NC05MjZmLTIyMTJlYWFkNDliYQ==&encode=on",
      "url": "https://www.ppomppu.co.kr/zboard/view.php?id=ppomppu&page=1&divpage=111&no=700416"
    },
    {
      "id": 13,
      "title": "[뽐뿌] 탄탄포크 돈목심 구이용(100g)",
      "productName": "탄탄포크 돈목심 구이용(100g)",
      "category": "festa",
      "source": "뽐뿌",
      "platform": "",
      "price": 990,
      "priceText": "990원",
      "shipping": "무료",
      "discount": 0,
      "createdAt": "2026-04-29T16:10:16.000Z",
      "deadlineAt": "",
      "deadlineText": "",
      "statusText": "",
      "expiresAt": "",
      "eventTags": [
        "할인페스타"
      ],
      "sourceCategory": "",
      "summary": "탄탄포크 돈목심 구이용(100g) 특가입니다. 990원, 무료.",
      "summaryPoints": [
        "가격: 990원",
        "배송: 무료"
      ],
      "originalUrl": "https://www.ppomppu.co.kr/zboard/view.php?id=ppomppu&page=1&divpage=111&no=700415",
      "purchaseUrl": "https://s.ppomppu.co.kr/?idno=ppomppu_700415&target=aHR0cHM6Ly9lbWFydC5zc2cuY29tL2l0ZW0vaXRlbVZpZXcuc3NnP2l0ZW1JZD0xMDAwMjY2MDQxNTMz&encode=on",
      "url": "https://www.ppomppu.co.kr/zboard/view.php?id=ppomppu&page=1&divpage=111&no=700415"
    },
    {
      "id": 14,
      "title": "[옥션] 국내산 햇갓김치 1.5kg",
      "productName": "국내산 햇갓김치 1.5kg",
      "category": "festa",
      "source": "뽐뿌",
      "platform": "옥션",
      "price": 8010,
      "priceText": "8,010원",
      "shipping": "무배",
      "discount": 0,
      "createdAt": "2026-04-29T15:58:11.000Z",
      "deadlineAt": "",
      "deadlineText": "",
      "statusText": "",
      "expiresAt": "",
      "eventTags": [
        "할인페스타"
      ],
      "sourceCategory": "",
      "summary": "국내산 햇갓김치 1.5kg 특가입니다. 옥션 기준 8,010원, 무배.",
      "summaryPoints": [
        "플랫폼: 옥션",
        "가격: 8,010원",
        "배송: 무배"
      ],
      "originalUrl": "https://www.ppomppu.co.kr/zboard/view.php?id=ppomppu&page=1&divpage=111&no=700414",
      "purchaseUrl": "https://s.ppomppu.co.kr/?idno=ppomppu_700414&target=aHR0cHM6Ly9taXRlbS5hdWN0aW9uLmNvLmtyL3ZpcD9pdGVtTm89QzI0NTE3MDU5Mw==&encode=on",
      "url": "https://www.ppomppu.co.kr/zboard/view.php?id=ppomppu&page=1&divpage=111&no=700414"
    },
    {
      "id": 15,
      "title": "[네이버] GS25 와인25플러스 모바일상품권 3만원권",
      "productName": "GS25 와인25플러스 모바일상품권 3만원권",
      "category": "voucher",
      "source": "뽐뿌",
      "platform": "네이버",
      "price": 25920,
      "priceText": "25,920원",
      "shipping": "무료",
      "discount": 0,
      "createdAt": "2026-04-29T15:45:04.000Z",
      "deadlineAt": "",
      "deadlineText": "",
      "statusText": "",
      "expiresAt": "",
      "eventTags": [],
      "sourceCategory": "",
      "summary": "GS25 와인25플러스 모바일상품권 3만원권 특가입니다. 네이버 기준 25,920원, 무료.",
      "summaryPoints": [
        "플랫폼: 네이버",
        "가격: 25,920원",
        "배송: 무료"
      ],
      "originalUrl": "https://www.ppomppu.co.kr/zboard/view.php?id=ppomppu&page=1&divpage=111&no=700413",
      "purchaseUrl": "https://s.ppomppu.co.kr/?idno=ppomppu_700413&target=aHR0cHM6Ly9tLmJyYW5kLm5hdmVyLmNvbS9nczI1L3Byb2R1Y3RzLzEzMjY4MjY3OTU1&encode=on",
      "url": "https://www.ppomppu.co.kr/zboard/view.php?id=ppomppu&page=1&divpage=111&no=700413"
    },
    {
      "id": 16,
      "title": "[뽐뿌] 파리바게뜨 버니&베어 축하파티 케이크 27%할인",
      "productName": "파리바게뜨 버니&베어 축하파티 케이크 27%할인",
      "category": "dessert",
      "source": "뽐뿌",
      "platform": "",
      "price": 24050,
      "priceText": "24,050원",
      "shipping": "무료",
      "discount": 27,
      "createdAt": "2026-04-29T15:38:27.000Z",
      "deadlineAt": "",
      "deadlineText": "",
      "statusText": "",
      "expiresAt": "",
      "eventTags": [
        "식품"
      ],
      "sourceCategory": "",
      "summary": "파리바게뜨 버니&베어 축하파티 케이크 27%할인 특가입니다. 24,050원, 무료.",
      "summaryPoints": [
        "가격: 24,050원",
        "배송: 무료"
      ],
      "originalUrl": "https://www.ppomppu.co.kr/zboard/view.php?id=ppomppu&page=1&divpage=111&no=700412",
      "purchaseUrl": "https://s.ppomppu.co.kr/?idno=ppomppu_700412&target=aHR0cHM6Ly9naWZ0Lmtha2FvLmNvbS9wcm9kdWN0LzEzNDIxMjI5P2Jhbm5lcl9pZD0xNDQ4JmNhbXBhaWduX2NvZGU9bnVsbA==&encode=on",
      "url": "https://www.ppomppu.co.kr/zboard/view.php?id=ppomppu&page=1&divpage=111&no=700412"
    },
    {
      "id": 17,
      "title": "[롯데온] 나랑드사이다 345ml 3종 택 1박스 총 24캔",
      "productName": "나랑드사이다 345ml 3종 택 1박스 총 24캔",
      "category": "food-other",
      "source": "뽐뿌",
      "platform": "롯데온",
      "price": 11560,
      "priceText": "11,560원",
      "shipping": "무료",
      "discount": 0,
      "createdAt": "2026-04-29T15:34:31.000Z",
      "deadlineAt": "",
      "deadlineText": "",
      "statusText": "",
      "expiresAt": "",
      "eventTags": [
        "식품"
      ],
      "sourceCategory": "",
      "summary": "나랑드사이다 345ml 3종 택 1박스 총 24캔 특가입니다. 롯데온 기준 11,560원, 무료.",
      "summaryPoints": [
        "플랫폼: 롯데온",
        "가격: 11,560원",
        "배송: 무료"
      ],
      "originalUrl": "https://www.ppomppu.co.kr/zboard/view.php?id=ppomppu&page=1&divpage=111&no=700411",
      "purchaseUrl": "https://s.ppomppu.co.kr/?idno=ppomppu_700411&target=aHR0cHM6Ly93d3cubG90dGVvbi5jb20vcC9wcm9kdWN0L0xPMjY0NjIyOTg0OQ==&encode=on",
      "url": "https://www.ppomppu.co.kr/zboard/view.php?id=ppomppu&page=1&divpage=111&no=700411"
    },
    {
      "id": 18,
      "title": "[오늘의집] 하림 자연실록 생닭 1,050g 2봉",
      "productName": "하림 자연실록 생닭 1,050g 2봉",
      "category": "festa",
      "source": "뽐뿌",
      "platform": "오늘의집",
      "price": 13818,
      "priceText": "13,818원",
      "shipping": "무료",
      "discount": 0,
      "createdAt": "2026-04-29T15:33:07.000Z",
      "deadlineAt": "",
      "deadlineText": "",
      "statusText": "",
      "expiresAt": "",
      "eventTags": [
        "할인페스타"
      ],
      "sourceCategory": "",
      "summary": "하림 자연실록 생닭 1,050g 2봉 특가입니다. 오늘의집 기준 13,818원, 무료.",
      "summaryPoints": [
        "플랫폼: 오늘의집",
        "가격: 13,818원",
        "배송: 무료"
      ],
      "originalUrl": "https://www.ppomppu.co.kr/zboard/view.php?id=ppomppu&page=1&divpage=111&no=700410",
      "purchaseUrl": "https://s.ppomppu.co.kr/?idno=ppomppu_700410&target=aHR0cHM6Ly9zdG9yZS5vaG91LnNlL2dvb2RzLzM5Nzk2Mjg=&encode=on",
      "url": "https://www.ppomppu.co.kr/zboard/view.php?id=ppomppu&page=1&divpage=111&no=700410"
    },
    {
      "id": 19,
      "title": "[네이버페이] 일일적립, 클릭 23원, 라이브예고 7원",
      "productName": "일일적립, 클릭 23원, 라이브예고 7원",
      "category": "festa",
      "source": "루리웹",
      "platform": "네이버페이",
      "price": 23,
      "priceText": "23원",
      "shipping": "",
      "discount": 0,
      "createdAt": "2026-04-29T15:11:00.000Z",
      "deadlineAt": "",
      "deadlineText": "",
      "statusText": "",
      "expiresAt": "",
      "eventTags": [
        "적립",
        "페이적립",
        "라이브특가"
      ],
      "sourceCategory": "BEST",
      "summary": "일일적립, 클릭 23원, 라이브예고 7원 특가입니다. 네이버페이 기준 23원.",
      "summaryPoints": [
        "플랫폼: 네이버페이",
        "가격: 23원"
      ],
      "originalUrl": "https://bbs.ruliweb.com/market/board/1020/read/103779?",
      "purchaseUrl": "",
      "url": "https://bbs.ruliweb.com/market/board/1020/read/103779?"
    },
    {
      "id": 20,
      "title": "[네이버] 순수식품 멀티 종합비타민 4박스",
      "productName": "순수식품 멀티 종합비타민 4박스",
      "category": "food-other",
      "source": "딜바다 국내",
      "platform": "네이버",
      "price": 28350,
      "priceText": "28,350원",
      "shipping": "무료",
      "discount": 0,
      "createdAt": "2026-04-29T15:06:00.000Z",
      "deadlineAt": "",
      "deadlineText": "",
      "statusText": "",
      "expiresAt": "",
      "eventTags": [
        "식품"
      ],
      "sourceCategory": "식품/건강",
      "summary": "순수식품 멀티 종합비타민 4박스 특가입니다. 네이버 기준 28,350원, 무료.",
      "summaryPoints": [
        "플랫폼: 네이버",
        "가격: 28,350원",
        "배송: 무료"
      ],
      "originalUrl": "https://www.dealbada.com/bbs/board.php?bo_table=deal_domestic&wr_id=569151&page=1",
      "purchaseUrl": "https://www.dealbada.com/bbs/link.php?bo_table=deal_domestic&wr_id=569151&no=2&page=1",
      "url": "https://www.dealbada.com/bbs/board.php?bo_table=deal_domestic&wr_id=569151&page=1"
    },
    {
      "id": 21,
      "title": "[루리웹] 오후 4~7시 선착순 50명 어메이징더블버거 1900원(...",
      "productName": "오후 4~7시 선착순 50명 어메이징더블버거 1900원(...",
      "category": "festa",
      "source": "루리웹",
      "platform": "",
      "price": 1900,
      "priceText": "1900원",
      "shipping": "",
      "discount": 0,
      "createdAt": "2026-04-29T15:05:00.000Z",
      "deadlineAt": "",
      "deadlineText": "",
      "statusText": "선착순",
      "expiresAt": "",
      "eventTags": [
        "할인페스타"
      ],
      "sourceCategory": "음식",
      "summary": "오후 4~7시 선착순 50명 어메이징더블버거 1900원(... 특가입니다. 1900원. 조건: 선착순 50명.",
      "summaryPoints": [
        "가격: 1900원",
        "조건: 선착순 50명"
      ],
      "originalUrl": "https://bbs.ruliweb.com/market/board/1020/read/103778?",
      "purchaseUrl": "",
      "url": "https://bbs.ruliweb.com/market/board/1020/read/103778?"
    },
    {
      "id": 22,
      "title": "[네이버페이] 2026-04-30 일일적립, 클릭 23원",
      "productName": "2026-04-30 일일적립, 클릭 23원",
      "category": "festa",
      "source": "개드립",
      "platform": "네이버페이",
      "price": 23,
      "priceText": "23원",
      "shipping": "",
      "discount": 0,
      "createdAt": "2026-04-29T15:00:00.000Z",
      "deadlineAt": "",
      "deadlineText": "",
      "statusText": "",
      "expiresAt": "",
      "eventTags": [
        "적립",
        "페이적립"
      ],
      "sourceCategory": "기타",
      "summary": "2026-04-30 일일적립, 클릭 23원 특가입니다. 네이버페이 기준 23원.",
      "summaryPoints": [
        "플랫폼: 네이버페이",
        "가격: 23원"
      ],
      "originalUrl": "https://www.dogdrip.net/hotdeal/699156721?sort_index=popular&page=1",
      "purchaseUrl": "https://new-m.pay.naver.com/historybenefit/home",
      "url": "https://www.dogdrip.net/hotdeal/699156721?sort_index=popular&page=1"
    },
    {
      "id": 23,
      "title": "[G마켓] 1:14 포르쉐 911 GT3 RS RC카 800pcs",
      "productName": "1:14 포르쉐 911 GT3 RS RC카 800pcs",
      "category": "electronics",
      "source": "뽐뿌",
      "platform": "G마켓",
      "price": 33900,
      "priceText": "33,900원",
      "shipping": "무료",
      "discount": 0,
      "createdAt": "2026-04-28T15:00:00.000Z",
      "deadlineAt": "",
      "deadlineText": "",
      "statusText": "",
      "expiresAt": "",
      "eventTags": [],
      "sourceCategory": "",
      "summary": "1:14 포르쉐 911 GT3 RS RC카 800pcs 특가입니다. G마켓 기준 33,900원, 무료.",
      "summaryPoints": [
        "플랫폼: G마켓",
        "가격: 33,900원",
        "배송: 무료"
      ],
      "originalUrl": "https://www.ppomppu.co.kr/zboard/view.php?id=ppomppu&page=1&divpage=111&no=700301",
      "purchaseUrl": "https://s.ppomppu.co.kr/?idno=ppomppu_700301&target=aHR0cHM6Ly9pdGVtLmdtYXJrZXQuY28ua3IvSXRlbT9nb29kc2NvZGU9NDczNzEzMTY1NQ==&encode=on",
      "url": "https://www.ppomppu.co.kr/zboard/view.php?id=ppomppu&page=1&divpage=111&no=700301"
    },
    {
      "id": 24,
      "title": "[알리익스프레스] 5월 Choice Day 정보 안내",
      "productName": "5월 Choice Day 정보 안내",
      "category": "overseas",
      "source": "알리뽐뿌",
      "platform": "알리익스프레스",
      "price": 0,
      "priceText": "",
      "shipping": "",
      "discount": 0,
      "createdAt": "2026-04-28T15:00:00.000Z",
      "deadlineAt": "",
      "deadlineText": "",
      "statusText": "",
      "expiresAt": "",
      "eventTags": [],
      "sourceCategory": "",
      "summary": "5월 Choice Day 정보 안내 특가입니다. 알리익스프레스 기준.",
      "summaryPoints": [
        "플랫폼: 알리익스프레스"
      ],
      "originalUrl": "https://www.ppomppu.co.kr/zboard/view.php?id=ppomppu8&page=1&divpage=15&no=87166",
      "purchaseUrl": "",
      "url": "https://www.ppomppu.co.kr/zboard/view.php?id=ppomppu8&page=1&divpage=15&no=87166"
    },
    {
      "id": 25,
      "title": "[알리뽐뿌] 풀라스 프리미엄 충전식 보풀제거기(31,136원), 폴더블 핸디형 스팀다리미...",
      "productName": "풀라스 프리미엄 충전식 보풀제거기(31,136원), 폴더블 핸디형 스팀다리미...",
      "category": "overseas",
      "source": "알리뽐뿌",
      "platform": "알리뽐뿌",
      "price": 31136,
      "priceText": "31,136원",
      "shipping": "",
      "discount": 0,
      "createdAt": "2026-04-28T15:00:00.000Z",
      "deadlineAt": "",
      "deadlineText": "",
      "statusText": "",
      "expiresAt": "",
      "eventTags": [],
      "sourceCategory": "",
      "summary": "풀라스 프리미엄 충전식 보풀제거기(31,136원), 폴더블 핸디형 스팀다리미... 특가입니다. 알리뽐뿌 기준 31,136원.",
      "summaryPoints": [
        "플랫폼: 알리뽐뿌",
        "가격: 31,136원"
      ],
      "originalUrl": "https://www.ppomppu.co.kr/zboard/view.php?id=ppomppu8&page=1&divpage=15&no=87192",
      "purchaseUrl": "https://s.ppomppu.co.kr/?idno=ppomppu8_87192&target=aHR0cHM6Ly9rby5hbGlleHByZXNzLmNvbS9pdGVtLzEwMDUwMTE4OTA4OTA3NzAuaHRtbA==&encode=on",
      "url": "https://www.ppomppu.co.kr/zboard/view.php?id=ppomppu8&page=1&divpage=15&no=87192"
    },
    {
      "id": 26,
      "title": "[알리뽐뿌] 충전식 USB 회전 헤드 팬 야간 조명 에어쿨러($14.72)/무료",
      "productName": "충전식 USB 회전 헤드 팬 야간 조명 에어쿨러($14.72)/무료",
      "category": "overseas",
      "source": "알리뽐뿌",
      "platform": "알리뽐뿌",
      "price": 0,
      "priceText": "",
      "shipping": "무료",
      "discount": 0,
      "createdAt": "2026-04-28T15:00:00.000Z",
      "deadlineAt": "",
      "deadlineText": "",
      "statusText": "",
      "expiresAt": "",
      "eventTags": [],
      "sourceCategory": "",
      "summary": "충전식 USB 회전 헤드 팬 야간 조명 에어쿨러($14.72)/무료 특가입니다. 알리뽐뿌 기준 무료.",
      "summaryPoints": [
        "플랫폼: 알리뽐뿌",
        "배송: 무료"
      ],
      "originalUrl": "https://www.ppomppu.co.kr/zboard/view.php?id=ppomppu8&page=1&divpage=15&no=87191",
      "purchaseUrl": "https://s.ppomppu.co.kr/?idno=ppomppu8_87191&target=aHR0cHM6Ly9rby5hbGlleHByZXNzLmNvbS9pdGVtLzEwMDUwMTE4OTEzMDYyMzMuaHRtbA==&encode=on",
      "url": "https://www.ppomppu.co.kr/zboard/view.php?id=ppomppu8&page=1&divpage=15&no=87191"
    },
    {
      "id": 27,
      "title": "[알리뽐뿌] 저소음 BLDC 무선 접이식 3단 스탠드 선풍기(31,810원), BLDC 충전식 무선 탁상...",
      "productName": "저소음 BLDC 무선 접이식 3단 스탠드 선풍기(31,810원), BLDC 충전식 무선 탁상...",
      "category": "overseas",
      "source": "알리뽐뿌",
      "platform": "알리뽐뿌",
      "price": 31810,
      "priceText": "31,810원",
      "shipping": "",
      "discount": 0,
      "createdAt": "2026-04-28T15:00:00.000Z",
      "deadlineAt": "",
      "deadlineText": "",
      "statusText": "",
      "expiresAt": "",
      "eventTags": [],
      "sourceCategory": "",
      "summary": "저소음 BLDC 무선 접이식 3단 스탠드 선풍기(31,810원), BLDC 충전식 무선 탁상... 특가입니다. 알리뽐뿌 기준 31,810원.",
      "summaryPoints": [
        "플랫폼: 알리뽐뿌",
        "가격: 31,810원"
      ],
      "originalUrl": "https://www.ppomppu.co.kr/zboard/view.php?id=ppomppu8&page=1&divpage=15&no=87190",
      "purchaseUrl": "https://s.ppomppu.co.kr/?idno=ppomppu8_87190&target=aHR0cHM6Ly9rby5hbGlleHByZXNzLmNvbS9pdGVtLzEwMDUwMTE5MzEzMTI1MjYuaHRtbA==&encode=on",
      "url": "https://www.ppomppu.co.kr/zboard/view.php?id=ppomppu8&page=1&divpage=15&no=87190"
    },
    {
      "id": 28,
      "title": "[알리뽐뿌] 펩시 차량용 방향제 (7,000원), 차싹 원터치 에어컨 탈취제(6,114원)/무료",
      "productName": "펩시 차량용 방향제 (7,000원), 차싹 원터치 에어컨 탈취제(6,114원)/무료",
      "category": "overseas",
      "source": "알리뽐뿌",
      "platform": "알리뽐뿌",
      "price": 7000,
      "priceText": "7,000원",
      "shipping": "무료",
      "discount": 0,
      "createdAt": "2026-04-28T15:00:00.000Z",
      "deadlineAt": "",
      "deadlineText": "",
      "statusText": "",
      "expiresAt": "",
      "eventTags": [],
      "sourceCategory": "",
      "summary": "펩시 차량용 방향제 (7,000원), 차싹 원터치 에어컨 탈취제(6,114원)/무료 특가입니다. 알리뽐뿌 기준 7,000원, 무료.",
      "summaryPoints": [
        "플랫폼: 알리뽐뿌",
        "가격: 7,000원",
        "배송: 무료"
      ],
      "originalUrl": "https://www.ppomppu.co.kr/zboard/view.php?id=ppomppu8&page=1&divpage=15&no=87189",
      "purchaseUrl": "https://s.ppomppu.co.kr/?idno=ppomppu8_87189&target=aHR0cHM6Ly9rby5hbGlleHByZXNzLmNvbS9pdGVtLzEwMDUwMTA2NzU0MzMzNjMuaHRtbD8=&encode=on",
      "url": "https://www.ppomppu.co.kr/zboard/view.php?id=ppomppu8&page=1&divpage=15&no=87189"
    },
    {
      "id": 29,
      "title": "[알리뽐뿌] 현대모비스에어컨필터전용 방향제탈취제(9,306원)/무료",
      "productName": "현대모비스에어컨필터전용 방향제탈취제(9,306원)/무료",
      "category": "overseas",
      "source": "알리뽐뿌",
      "platform": "알리뽐뿌",
      "price": 9306,
      "priceText": "9,306원",
      "shipping": "무료",
      "discount": 0,
      "createdAt": "2026-04-28T15:00:00.000Z",
      "deadlineAt": "",
      "deadlineText": "",
      "statusText": "",
      "expiresAt": "",
      "eventTags": [],
      "sourceCategory": "",
      "summary": "현대모비스에어컨필터전용 방향제탈취제(9,306원)/무료 특가입니다. 알리뽐뿌 기준 9,306원, 무료.",
      "summaryPoints": [
        "플랫폼: 알리뽐뿌",
        "가격: 9,306원",
        "배송: 무료"
      ],
      "originalUrl": "https://www.ppomppu.co.kr/zboard/view.php?id=ppomppu8&page=1&divpage=15&no=87188",
      "purchaseUrl": "https://s.ppomppu.co.kr/?idno=ppomppu8_87188&target=aHR0cHM6Ly9rby5hbGlleHByZXNzLmNvbS9pdGVtLzEwMDUwMTA3OTI1MDM5MTEuaHRtbA==&encode=on",
      "url": "https://www.ppomppu.co.kr/zboard/view.php?id=ppomppu8&page=1&divpage=15&no=87188"
    },
    {
      "id": 30,
      "title": "[알리뽐뿌] 이지라이프 라운드 소파 사이드 테이블 (9,845원) 스퀘어 침대 협탁 (12,166원) 사이...",
      "productName": "이지라이프 라운드 소파 사이드 테이블 (9,845원) 스퀘어 침대 협탁 (12,166원) 사이...",
      "category": "overseas",
      "source": "알리뽐뿌",
      "platform": "알리뽐뿌",
      "price": 9845,
      "priceText": "9,845원",
      "shipping": "",
      "discount": 0,
      "createdAt": "2026-04-28T15:00:00.000Z",
      "deadlineAt": "",
      "deadlineText": "",
      "statusText": "",
      "expiresAt": "",
      "eventTags": [],
      "sourceCategory": "",
      "summary": "이지라이프 라운드 소파 사이드 테이블 (9,845원) 스퀘어 침대 협탁 (12,166원) 사이... 특가입니다. 알리뽐뿌 기준 9,845원.",
      "summaryPoints": [
        "플랫폼: 알리뽐뿌",
        "가격: 9,845원"
      ],
      "originalUrl": "https://www.ppomppu.co.kr/zboard/view.php?id=ppomppu8&page=1&divpage=15&no=87187",
      "purchaseUrl": "https://s.ppomppu.co.kr/?idno=ppomppu8_87167&target=aHR0cHM6Ly9rby5hbGlleHByZXNzLmNvbS9pdGVtLzEwMDUwMTAyMTYyODgwNDYuaHRtbA==&encode=on",
      "url": "https://www.ppomppu.co.kr/zboard/view.php?id=ppomppu8&page=1&divpage=15&no=87187"
    },
    {
      "id": 31,
      "title": "[알리뽐뿌] 푸드앤픽 새청무 20kg 쌀 햅쌀 백미",
      "productName": "푸드앤픽 새청무 20kg 쌀 햅쌀 백미",
      "category": "overseas",
      "source": "알리뽐뿌",
      "platform": "알리뽐뿌",
      "price": 54540,
      "priceText": "54,540원",
      "shipping": "무배",
      "discount": 0,
      "createdAt": "2026-04-28T15:00:00.000Z",
      "deadlineAt": "",
      "deadlineText": "",
      "statusText": "",
      "expiresAt": "",
      "eventTags": [],
      "sourceCategory": "",
      "summary": "푸드앤픽 새청무 20kg 쌀 햅쌀 백미 특가입니다. 알리뽐뿌 기준 54,540원, 무배.",
      "summaryPoints": [
        "플랫폼: 알리뽐뿌",
        "가격: 54,540원",
        "배송: 무배"
      ],
      "originalUrl": "https://www.ppomppu.co.kr/zboard/view.php?id=ppomppu8&page=1&divpage=15&no=87185",
      "purchaseUrl": "https://s.ppomppu.co.kr/?idno=ppomppu8_87185&target=aHR0cHM6Ly93d3cuYWxpZXhwcmVzcy5jb20vaXRlbS8xMDA1MDEwNjgxODU3MzA4Lmh0bWw=&encode=on",
      "url": "https://www.ppomppu.co.kr/zboard/view.php?id=ppomppu8&page=1&divpage=15&no=87185"
    },
    {
      "id": 32,
      "title": "[알리뽐뿌] 로베르타디까메리노 차량용 방향제 2P (14,206원), 5+1 루엘디 프리미엄 차량용 ...",
      "productName": "로베르타디까메리노 차량용 방향제 2P (14,206원), 5+1 루엘디 프리미엄 차량용 ...",
      "category": "overseas",
      "source": "알리뽐뿌",
      "platform": "알리뽐뿌",
      "price": 14206,
      "priceText": "14,206원",
      "shipping": "",
      "discount": 0,
      "createdAt": "2026-04-28T15:00:00.000Z",
      "deadlineAt": "",
      "deadlineText": "",
      "statusText": "",
      "expiresAt": "",
      "eventTags": [],
      "sourceCategory": "",
      "summary": "로베르타디까메리노 차량용 방향제 2P (14,206원), 5+1 루엘디 프리미엄 차량용 ... 특가입니다. 알리뽐뿌 기준 14,206원.",
      "summaryPoints": [
        "플랫폼: 알리뽐뿌",
        "가격: 14,206원"
      ],
      "originalUrl": "https://www.ppomppu.co.kr/zboard/view.php?id=ppomppu8&page=1&divpage=15&no=87183",
      "purchaseUrl": "https://s.ppomppu.co.kr/?idno=ppomppu8_87183&target=aHR0cHM6Ly9rby5hbGlleHByZXNzLmNvbS9pdGVtLzEwMDUwMTA2NzU0MzMzNjMuaHRtbD8=&encode=on",
      "url": "https://www.ppomppu.co.kr/zboard/view.php?id=ppomppu8&page=1&divpage=15&no=87183"
    },
    {
      "id": 33,
      "title": "[알리뽐뿌] 알리특가) 블록 레이싱카 V12($4.48) 비행기 전투기 2.4G 원격 조종",
      "productName": "알리특가) 블록 레이싱카 V12($4.48) 비행기 전투기 2.4G 원격 조종",
      "category": "overseas",
      "source": "알리뽐뿌",
      "platform": "알리뽐뿌",
      "price": 0,
      "priceText": "",
      "shipping": "",
      "discount": 0,
      "createdAt": "2026-04-28T15:00:00.000Z",
      "deadlineAt": "",
      "deadlineText": "",
      "statusText": "",
      "expiresAt": "",
      "eventTags": [],
      "sourceCategory": "",
      "summary": "알리특가) 블록 레이싱카 V12($4.48) 비행기 전투기 2.4G 원격 조종 특가입니다. 알리뽐뿌 기준.",
      "summaryPoints": [
        "플랫폼: 알리뽐뿌"
      ],
      "originalUrl": "https://www.ppomppu.co.kr/zboard/view.php?id=ppomppu8&page=1&divpage=15&no=87182",
      "purchaseUrl": "https://s.ppomppu.co.kr/?idno=ppomppu8_87182&target=aHR0cHM6Ly9rby5hbGlleHByZXNzLmNvbS9pdGVtLzEwMDUwMDk1ODcwMjgyNzAuaHRtbA==&encode=on",
      "url": "https://www.ppomppu.co.kr/zboard/view.php?id=ppomppu8&page=1&divpage=15&no=87182"
    },
    {
      "id": 34,
      "title": "[알리뽐뿌] 최저가) 홀위트데이 당일생산 100% 통밀빵 1kg(8,287원), 글릿 프로틴 고단백 ...",
      "productName": "최저가) 홀위트데이 당일생산 100% 통밀빵 1kg(8,287원), 글릿 프로틴 고단백 ...",
      "category": "overseas",
      "source": "알리뽐뿌",
      "platform": "알리뽐뿌",
      "price": 8287,
      "priceText": "8,287원",
      "shipping": "",
      "discount": 0,
      "createdAt": "2026-04-28T15:00:00.000Z",
      "deadlineAt": "",
      "deadlineText": "",
      "statusText": "",
      "expiresAt": "",
      "eventTags": [],
      "sourceCategory": "",
      "summary": "최저가) 홀위트데이 당일생산 100% 통밀빵 1kg(8,287원), 글릿 프로틴 고단백 ... 특가입니다. 알리뽐뿌 기준 8,287원.",
      "summaryPoints": [
        "플랫폼: 알리뽐뿌",
        "가격: 8,287원"
      ],
      "originalUrl": "https://www.ppomppu.co.kr/zboard/view.php?id=ppomppu8&page=1&divpage=15&no=87181",
      "purchaseUrl": "https://s.ppomppu.co.kr/?idno=ppomppu8_87181&target=aHR0cHM6Ly9rby5hbGlleHByZXNzLmNvbS9pdGVtLzEwMDUwMTA3MDIwMDc1NjEuaHRtbA==&encode=on",
      "url": "https://www.ppomppu.co.kr/zboard/view.php?id=ppomppu8&page=1&divpage=15&no=87181"
    },
    {
      "id": 35,
      "title": "[알리뽐뿌] 국내생산 파로 영양 찰가래떡 야간 런칭 특가 국내최저가 4kg",
      "productName": "국내생산 파로 영양 찰가래떡 야간 런칭 특가 국내최저가 4kg",
      "category": "overseas",
      "source": "알리뽐뿌",
      "platform": "알리뽐뿌",
      "price": 26900,
      "priceText": "26900원",
      "shipping": "무배",
      "discount": 0,
      "createdAt": "2026-04-28T15:00:00.000Z",
      "deadlineAt": "",
      "deadlineText": "",
      "statusText": "",
      "expiresAt": "",
      "eventTags": [],
      "sourceCategory": "",
      "summary": "국내생산 파로 영양 찰가래떡 야간 런칭 특가 국내최저가 4kg 특가입니다. 알리뽐뿌 기준 26900원, 무배.",
      "summaryPoints": [
        "플랫폼: 알리뽐뿌",
        "가격: 26900원",
        "배송: 무배"
      ],
      "originalUrl": "https://www.ppomppu.co.kr/zboard/view.php?id=ppomppu8&page=1&divpage=15&no=87180",
      "purchaseUrl": "https://s.ppomppu.co.kr/?idno=ppomppu8_87180&target=aHR0cHM6Ly9rby5hbGlleHByZXNzLmNvbS9pdGVtLzEwMDUwMTIwODA2ODk5MjEuaHRtbD9nYXRld2F5QWRhcHQ9Z2xvMmtvcg==&encode=on",
      "url": "https://www.ppomppu.co.kr/zboard/view.php?id=ppomppu8&page=1&divpage=15&no=87180"
    },
    {
      "id": 36,
      "title": "[알리뽐뿌] Lefon 인체공학적 OLED 블루투스 버티컬 마우스",
      "productName": "Lefon 인체공학적 OLED 블루투스 버티컬 마우스",
      "category": "overseas",
      "source": "알리뽐뿌",
      "platform": "알리뽐뿌",
      "price": 0,
      "priceText": "",
      "shipping": "무료",
      "discount": 0,
      "createdAt": "2026-04-28T15:00:00.000Z",
      "deadlineAt": "",
      "deadlineText": "",
      "statusText": "",
      "expiresAt": "",
      "eventTags": [],
      "sourceCategory": "",
      "summary": "Lefon 인체공학적 OLED 블루투스 버티컬 마우스 특가입니다. 알리뽐뿌 기준 무료.",
      "summaryPoints": [
        "플랫폼: 알리뽐뿌",
        "배송: 무료"
      ],
      "originalUrl": "https://www.ppomppu.co.kr/zboard/view.php?id=ppomppu8&page=1&divpage=15&no=87179",
      "purchaseUrl": "https://s.ppomppu.co.kr/?idno=ppomppu8_87179&target=aHR0cHM6Ly9rby5hbGlleHByZXNzLmNvbS9pdGVtLzEwMDUwMDc2MTI5MjEyNDQuaHRtbD8=&encode=on",
      "url": "https://www.ppomppu.co.kr/zboard/view.php?id=ppomppu8&page=1&divpage=15&no=87179"
    },
    {
      "id": 37,
      "title": "[알리뽐뿌] 그린핑거 유아 스킨케어 로션 워시/워셔블 선크림 모음전",
      "productName": "그린핑거 유아 스킨케어 로션 워시/워셔블 선크림 모음전",
      "category": "overseas",
      "source": "알리뽐뿌",
      "platform": "알리뽐뿌",
      "price": 19326,
      "priceText": "19,326원",
      "shipping": "무료",
      "discount": 0,
      "createdAt": "2026-04-28T15:00:00.000Z",
      "deadlineAt": "",
      "deadlineText": "",
      "statusText": "",
      "expiresAt": "",
      "eventTags": [],
      "sourceCategory": "",
      "summary": "그린핑거 유아 스킨케어 로션 워시/워셔블 선크림 모음전 특가입니다. 알리뽐뿌 기준 19,326원, 무료.",
      "summaryPoints": [
        "플랫폼: 알리뽐뿌",
        "가격: 19,326원",
        "배송: 무료"
      ],
      "originalUrl": "https://www.ppomppu.co.kr/zboard/view.php?id=ppomppu8&page=1&divpage=15&no=87178",
      "purchaseUrl": "https://s.ppomppu.co.kr/?idno=ppomppu8_87178&target=aHR0cHM6Ly9hLmFsaWV4cHJlc3MuY29tL19jMzlKb1Vpag==&encode=on",
      "url": "https://www.ppomppu.co.kr/zboard/view.php?id=ppomppu8&page=1&divpage=15&no=87178"
    },
    {
      "id": 38,
      "title": "[알리뽐뿌] (알리 특가) JAIYORL 목어깨 허리 온열 지압 마사지기($29.65) 무배",
      "productName": "(알리 특가) JAIYORL 목어깨 허리 온열 지압 마사지기($29.65) 무배",
      "category": "overseas",
      "source": "알리뽐뿌",
      "platform": "알리뽐뿌",
      "price": 0,
      "priceText": "",
      "shipping": "무배",
      "discount": 0,
      "createdAt": "2026-04-28T15:00:00.000Z",
      "deadlineAt": "",
      "deadlineText": "",
      "statusText": "",
      "expiresAt": "",
      "eventTags": [],
      "sourceCategory": "",
      "summary": "(알리 특가) JAIYORL 목어깨 허리 온열 지압 마사지기($29.65) 무배 특가입니다. 알리뽐뿌 기준 무배.",
      "summaryPoints": [
        "플랫폼: 알리뽐뿌",
        "배송: 무배"
      ],
      "originalUrl": "https://www.ppomppu.co.kr/zboard/view.php?id=ppomppu8&page=1&divpage=15&no=87177",
      "purchaseUrl": "https://s.ppomppu.co.kr/?idno=ppomppu8_87177&target=aHR0cHM6Ly9rby5hbGlleHByZXNzLmNvbS9pdGVtLzEwMDUwMDgzNDE4NjMzOTAuaHRtbA==&encode=on",
      "url": "https://www.ppomppu.co.kr/zboard/view.php?id=ppomppu8&page=1&divpage=15&no=87177"
    },
    {
      "id": 39,
      "title": "[네이버페이] 2026-04-29 일일적립, 클릭 50원",
      "productName": "2026-04-29 일일적립, 클릭 50원",
      "category": "festa",
      "source": "개드립",
      "platform": "네이버페이",
      "price": 50,
      "priceText": "50원",
      "shipping": "",
      "discount": 0,
      "createdAt": "2026-04-28T15:00:00.000Z",
      "deadlineAt": "",
      "deadlineText": "",
      "statusText": "",
      "expiresAt": "",
      "eventTags": [
        "적립",
        "페이적립"
      ],
      "sourceCategory": "기타",
      "summary": "2026-04-29 일일적립, 클릭 50원 특가입니다. 네이버페이 기준 50원.",
      "summaryPoints": [
        "플랫폼: 네이버페이",
        "가격: 50원"
      ],
      "originalUrl": "https://www.dogdrip.net/hotdeal/698993760?sort_index=popular&page=1",
      "purchaseUrl": "https://new-m.pay.naver.com/historybenefit/home",
      "url": "https://www.dogdrip.net/hotdeal/698993760?sort_index=popular&page=1"
    },
    {
      "id": 40,
      "title": "[알리익스프레스] 5월 초이스데이 온가족 행복위크 (5월1일(금)~5월7...",
      "productName": "5월 초이스데이 온가족 행복위크 (5월1일(금)~5월7...",
      "category": "overseas",
      "source": "루리웹",
      "platform": "알리익스프레스",
      "price": 0,
      "priceText": "",
      "shipping": "",
      "discount": 0,
      "createdAt": "2026-04-28T15:00:00.000Z",
      "deadlineAt": "",
      "deadlineText": "",
      "statusText": "",
      "expiresAt": "",
      "eventTags": [],
      "sourceCategory": "상품권",
      "summary": "5월 초이스데이 온가족 행복위크 (5월1일(금)~5월7... 특가입니다. 알리익스프레스 기준.",
      "summaryPoints": [
        "플랫폼: 알리익스프레스"
      ],
      "originalUrl": "https://bbs.ruliweb.com/market/board/1020/read/103769?",
      "purchaseUrl": "https://web.ruliweb.com/link.php?ol=https%3A%2F%2Fwww.aliexpress.com%2Fssr%2F300003014%2FKR5CDMainVenue%3FdisableNav%3DYES%26pha_manifest%3Dssr%26_immersiveMode%3Dtrue%26businessCode%3Dguide&bbs=1020",
      "url": "https://bbs.ruliweb.com/market/board/1020/read/103769?"
    },
    {
      "id": 41,
      "title": "[지마켓] 광동 옥수수수염차 1.85L 6병 (8,900원)",
      "productName": "광동 옥수수수염차 1.85L 6병 (8,900원)",
      "category": "festa",
      "source": "루리웹",
      "platform": "지마켓",
      "price": 8900,
      "priceText": "8,900원",
      "shipping": "",
      "discount": 0,
      "createdAt": "2026-04-28T15:00:00.000Z",
      "deadlineAt": "",
      "deadlineText": "",
      "statusText": "",
      "expiresAt": "",
      "eventTags": [
        "할인페스타"
      ],
      "sourceCategory": "BEST",
      "summary": "광동 옥수수수염차 1.85L 6병 (8,900원) 특가입니다. 지마켓 기준 8,900원.",
      "summaryPoints": [
        "플랫폼: 지마켓",
        "가격: 8,900원"
      ],
      "originalUrl": "https://bbs.ruliweb.com/market/board/1020/read/103774?",
      "purchaseUrl": "https://web.ruliweb.com/link.php?ol=https%3A%2F%2Fm.gmarket.co.kr%2Fvi%2Fproduct%2F4672835073&bbs=1020",
      "url": "https://bbs.ruliweb.com/market/board/1020/read/103774?"
    },
    {
      "id": 42,
      "title": "[루리웹] 라이프익스텐션 투퍼 종합비타민 60정 (12,485원/조건무...",
      "productName": "라이프익스텐션 투퍼 종합비타민 60정 (12,485원/조건무...",
      "category": "festa",
      "source": "루리웹",
      "platform": "",
      "price": 12485,
      "priceText": "12,485원",
      "shipping": "",
      "discount": 0,
      "createdAt": "2026-04-28T15:00:00.000Z",
      "deadlineAt": "",
      "deadlineText": "",
      "statusText": "",
      "expiresAt": "",
      "eventTags": [
        "할인페스타"
      ],
      "sourceCategory": "BEST",
      "summary": "라이프익스텐션 투퍼 종합비타민 60정 (12,485원/조건무... 특가입니다. 12,485원.",
      "summaryPoints": [
        "가격: 12,485원"
      ],
      "originalUrl": "https://bbs.ruliweb.com/market/board/1020/read/103772?",
      "purchaseUrl": "https://web.ruliweb.com/link.php?ol=https%3A%2F%2Fkr.iherb.com%2Fpr%2Flife-extension-two-per-day-multivitamin-60-tablets%2F86455&bbs=1020",
      "url": "https://bbs.ruliweb.com/market/board/1020/read/103772?"
    },
    {
      "id": 43,
      "title": "[루리웹] 네이버페이로 12000원 결제시 5000원 할인 (4/29...",
      "productName": "네이버페이로 12000원 결제시 5000원 할인 (4/29...",
      "category": "festa",
      "source": "루리웹",
      "platform": "",
      "price": 12000,
      "priceText": "12000원",
      "shipping": "",
      "discount": 0,
      "createdAt": "2026-04-28T15:00:00.000Z",
      "deadlineAt": "",
      "deadlineText": "",
      "statusText": "",
      "expiresAt": "",
      "eventTags": [
        "페이적립"
      ],
      "sourceCategory": "BEST",
      "summary": "네이버페이로 12000원 결제시 5000원 할인 (4/29... 특가입니다. 12000원.",
      "summaryPoints": [
        "가격: 12000원"
      ],
      "originalUrl": "https://bbs.ruliweb.com/market/board/1020/read/103766?",
      "purchaseUrl": "",
      "url": "https://bbs.ruliweb.com/market/board/1020/read/103766?"
    },
    {
      "id": 44,
      "title": "[루리웹] Surfshark VPN 2개월 52원 (수수료 포함 약 ...",
      "productName": "Surfshark VPN 2개월 52원 (수수료 포함 약 ...",
      "category": "electronics",
      "source": "루리웹",
      "platform": "",
      "price": 52,
      "priceText": "52원",
      "shipping": "",
      "discount": 0,
      "createdAt": "2026-04-28T15:00:00.000Z",
      "deadlineAt": "",
      "deadlineText": "",
      "statusText": "",
      "expiresAt": "",
      "eventTags": [],
      "sourceCategory": "PC/가전",
      "summary": "Surfshark VPN 2개월 52원 (수수료 포함 약 ... 특가입니다. 52원.",
      "summaryPoints": [
        "가격: 52원"
      ],
      "originalUrl": "https://bbs.ruliweb.com/market/board/1020/read/103773?",
      "purchaseUrl": "",
      "url": "https://bbs.ruliweb.com/market/board/1020/read/103773?"
    },
    {
      "id": 45,
      "title": "[네이버] 카카오페이지 상품권 1만원,3만원권 할인 8,770원, 26,3...",
      "productName": "카카오페이지 상품권 1만원,3만원권 할인 8,770원, 26,3...",
      "category": "voucher",
      "source": "루리웹",
      "platform": "네이버",
      "price": 8770,
      "priceText": "8,770원",
      "shipping": "",
      "discount": 0,
      "createdAt": "2026-04-28T15:00:00.000Z",
      "deadlineAt": "",
      "deadlineText": "",
      "statusText": "",
      "expiresAt": "",
      "eventTags": [],
      "sourceCategory": "상품권",
      "summary": "카카오페이지 상품권 1만원,3만원권 할인 8,770원, 26,3... 특가입니다. 네이버 기준 8,770원.",
      "summaryPoints": [
        "플랫폼: 네이버",
        "가격: 8,770원"
      ],
      "originalUrl": "https://bbs.ruliweb.com/market/board/1020/read/103771?",
      "purchaseUrl": "",
      "url": "https://bbs.ruliweb.com/market/board/1020/read/103771?"
    },
    {
      "id": 46,
      "title": "[루리웹] Dead by Daylight 할인 (8,600원)",
      "productName": "Dead by Daylight 할인 (8,600원)",
      "category": "game",
      "source": "루리웹",
      "platform": "",
      "price": 8600,
      "priceText": "8,600원",
      "shipping": "",
      "discount": 0,
      "createdAt": "2026-04-28T15:00:00.000Z",
      "deadlineAt": "",
      "deadlineText": "",
      "statusText": "",
      "expiresAt": "",
      "eventTags": [],
      "sourceCategory": "게임S/W",
      "summary": "Dead by Daylight 할인 (8,600원) 특가입니다. 8,600원.",
      "summaryPoints": [
        "가격: 8,600원"
      ],
      "originalUrl": "https://bbs.ruliweb.com/market/board/1020/read/103768?",
      "purchaseUrl": "",
      "url": "https://bbs.ruliweb.com/market/board/1020/read/103768?"
    },
    {
      "id": 47,
      "title": "[네이버] 웅진애사비500ml 24개+파인애플500ml 24개(24,910...",
      "productName": "웅진애사비500ml 24개+파인애플500ml 24개(24,910...",
      "category": "festa",
      "source": "루리웹",
      "platform": "네이버",
      "price": 0,
      "priceText": "",
      "shipping": "",
      "discount": 0,
      "createdAt": "2026-04-28T15:00:00.000Z",
      "deadlineAt": "",
      "deadlineText": "",
      "statusText": "",
      "expiresAt": "",
      "eventTags": [
        "할인페스타"
      ],
      "sourceCategory": "음식",
      "summary": "웅진애사비500ml 24개+파인애플500ml 24개(24,910... 특가입니다. 네이버 기준.",
      "summaryPoints": [
        "플랫폼: 네이버"
      ],
      "originalUrl": "https://bbs.ruliweb.com/market/board/1020/read/103765?",
      "purchaseUrl": "",
      "url": "https://bbs.ruliweb.com/market/board/1020/read/103765?"
    },
    {
      "id": 48,
      "title": "[루리웹] 플스포탈 화이트 288,000원 무배",
      "productName": "플스포탈 화이트 288,000원 무배",
      "category": "game",
      "source": "루리웹",
      "platform": "",
      "price": 288000,
      "priceText": "288,000원",
      "shipping": "무배",
      "discount": 0,
      "createdAt": "2026-04-28T15:00:00.000Z",
      "deadlineAt": "",
      "deadlineText": "",
      "statusText": "",
      "expiresAt": "",
      "eventTags": [],
      "sourceCategory": "게임S/W",
      "summary": "플스포탈 화이트 288,000원 무배 특가입니다. 288,000원, 무배.",
      "summaryPoints": [
        "가격: 288,000원",
        "배송: 무배"
      ],
      "originalUrl": "https://bbs.ruliweb.com/market/board/1020/read/103763?",
      "purchaseUrl": "",
      "url": "https://bbs.ruliweb.com/market/board/1020/read/103763?"
    },
    {
      "id": 49,
      "title": "[루리웹] 택틱스 오우거 18,600원 외 가격 다양",
      "productName": "택틱스 오우거 18,600원 외 가격 다양",
      "category": "game",
      "source": "루리웹",
      "platform": "",
      "price": 18600,
      "priceText": "18,600원",
      "shipping": "",
      "discount": 0,
      "createdAt": "2026-04-28T15:00:00.000Z",
      "deadlineAt": "",
      "deadlineText": "",
      "statusText": "",
      "expiresAt": "",
      "eventTags": [],
      "sourceCategory": "게임S/W",
      "summary": "택틱스 오우거 18,600원 외 가격 다양 특가입니다. 18,600원.",
      "summaryPoints": [
        "가격: 18,600원"
      ],
      "originalUrl": "https://bbs.ruliweb.com/market/board/1020/read/103762?",
      "purchaseUrl": "",
      "url": "https://bbs.ruliweb.com/market/board/1020/read/103762?"
    },
    {
      "id": 50,
      "title": "[롯데온] 하림 용가리 2봉+팝콘 1봉+너겟 100g (9,900원/무료...",
      "productName": "하림 용가리 2봉+팝콘 1봉+너겟 100g (9,900원/무료...",
      "category": "frozen",
      "source": "루리웹",
      "platform": "롯데온",
      "price": 9900,
      "priceText": "9,900원",
      "shipping": "무료",
      "discount": 0,
      "createdAt": "2026-04-28T15:00:00.000Z",
      "deadlineAt": "",
      "deadlineText": "",
      "statusText": "",
      "expiresAt": "",
      "eventTags": [
        "식품"
      ],
      "sourceCategory": "음식",
      "summary": "하림 용가리 2봉+팝콘 1봉+너겟 100g (9,900원/무료... 특가입니다. 롯데온 기준 9,900원, 무료.",
      "summaryPoints": [
        "플랫폼: 롯데온",
        "가격: 9,900원",
        "배송: 무료"
      ],
      "originalUrl": "https://bbs.ruliweb.com/market/board/1020/read/103761?",
      "purchaseUrl": "https://web.ruliweb.com/link.php?ol=https%3A%2F%2Fwww.lotteon.com%2Fp%2Fproduct%2FLO2657377422&bbs=1020",
      "url": "https://bbs.ruliweb.com/market/board/1020/read/103761?"
    },
    {
      "id": 51,
      "title": "[네이버] 프롭스165W PPS 20000mAh 기내반입 보조배터리(49,...",
      "productName": "프롭스165W PPS 20000mAh 기내반입 보조배터리(49,...",
      "category": "electronics",
      "source": "루리웹",
      "platform": "네이버",
      "price": 0,
      "priceText": "",
      "shipping": "",
      "discount": 0,
      "createdAt": "2026-04-28T15:00:00.000Z",
      "deadlineAt": "",
      "deadlineText": "",
      "statusText": "",
      "expiresAt": "",
      "eventTags": [],
      "sourceCategory": "PC/가전",
      "summary": "프롭스165W PPS 20000mAh 기내반입 보조배터리(49,... 특가입니다. 네이버 기준.",
      "summaryPoints": [
        "플랫폼: 네이버"
      ],
      "originalUrl": "https://bbs.ruliweb.com/market/board/1020/read/103760?",
      "purchaseUrl": "",
      "url": "https://bbs.ruliweb.com/market/board/1020/read/103760?"
    },
    {
      "id": 52,
      "title": "[루리웹] Chicken Chess Match 무료",
      "productName": "Chicken Chess Match 무료",
      "category": "game",
      "source": "루리웹",
      "platform": "",
      "price": 0,
      "priceText": "",
      "shipping": "무료",
      "discount": 0,
      "createdAt": "2026-04-28T15:00:00.000Z",
      "deadlineAt": "",
      "deadlineText": "",
      "statusText": "",
      "expiresAt": "",
      "eventTags": [],
      "sourceCategory": "게임S/W",
      "summary": "Chicken Chess Match 무료 특가입니다. 무료.",
      "summaryPoints": [
        "배송: 무료"
      ],
      "originalUrl": "https://bbs.ruliweb.com/market/board/1020/read/103759?",
      "purchaseUrl": "",
      "url": "https://bbs.ruliweb.com/market/board/1020/read/103759?"
    },
    {
      "id": 53,
      "title": "[네이버] 여름 가전 선풍기,서큘레이터 / 냉풍기 할인",
      "productName": "여름 가전 선풍기,서큘레이터 / 냉풍기 할인",
      "category": "electronics",
      "source": "딜바다 국내",
      "platform": "네이버",
      "price": 0,
      "priceText": "다양",
      "shipping": "무료",
      "discount": 0,
      "createdAt": "2026-04-28T15:00:00.000Z",
      "deadlineAt": "",
      "deadlineText": "",
      "statusText": "",
      "expiresAt": "",
      "eventTags": [],
      "sourceCategory": "가전",
      "summary": "여름 가전 선풍기,서큘레이터 / 냉풍기 할인 특가입니다. 네이버 기준 다양, 무료.",
      "summaryPoints": [
        "플랫폼: 네이버",
        "가격: 다양",
        "배송: 무료"
      ],
      "originalUrl": "https://www.dealbada.com/bbs/board.php?bo_table=deal_domestic&wr_id=569150&page=1",
      "purchaseUrl": "https://www.dealbada.com/bbs/link.php?bo_table=deal_domestic&wr_id=569150&no=1&page=1",
      "url": "https://www.dealbada.com/bbs/board.php?bo_table=deal_domestic&wr_id=569150&page=1"
    },
    {
      "id": 54,
      "title": "[딜바다 국내] 다낭/호이안 노팁 노옵션 3박5일",
      "productName": "다낭/호이안 노팁 노옵션 3박5일",
      "category": "festa",
      "source": "딜바다 국내",
      "platform": "",
      "price": 0,
      "priceText": "",
      "shipping": "무료",
      "discount": 0,
      "createdAt": "2026-04-28T15:00:00.000Z",
      "deadlineAt": "",
      "deadlineText": "",
      "statusText": "",
      "expiresAt": "",
      "eventTags": [
        "할인페스타"
      ],
      "sourceCategory": "기타",
      "summary": "다낭/호이안 노팁 노옵션 3박5일 특가입니다. 무료.",
      "summaryPoints": [
        "배송: 무료"
      ],
      "originalUrl": "https://www.dealbada.com/bbs/board.php?bo_table=deal_domestic&wr_id=569149&page=1",
      "purchaseUrl": "https://www.dealbada.com/bbs/link.php?bo_table=deal_domestic&wr_id=569149&no=1&page=1",
      "url": "https://www.dealbada.com/bbs/board.php?bo_table=deal_domestic&wr_id=569149&page=1"
    },
    {
      "id": 55,
      "title": "[지마켓] 무항생제인증 방사 유정란 60구",
      "productName": "무항생제인증 방사 유정란 60구",
      "category": "food-other",
      "source": "딜바다 국내",
      "platform": "지마켓",
      "price": 27330,
      "priceText": "27,330원",
      "shipping": "무료",
      "discount": 0,
      "createdAt": "2026-04-28T15:00:00.000Z",
      "deadlineAt": "",
      "deadlineText": "",
      "statusText": "",
      "expiresAt": "",
      "eventTags": [
        "식품"
      ],
      "sourceCategory": "식품/건강",
      "summary": "무항생제인증 방사 유정란 60구 특가입니다. 지마켓 기준 27,330원, 무료.",
      "summaryPoints": [
        "플랫폼: 지마켓",
        "가격: 27,330원",
        "배송: 무료"
      ],
      "originalUrl": "https://www.dealbada.com/bbs/board.php?bo_table=deal_domestic&wr_id=569148&page=1",
      "purchaseUrl": "https://www.dealbada.com/bbs/link.php?bo_table=deal_domestic&wr_id=569148&no=1&page=1",
      "url": "https://www.dealbada.com/bbs/board.php?bo_table=deal_domestic&wr_id=569148&page=1"
    },
    {
      "id": 56,
      "title": "[네이버] 한려담원 지리산 토종 흑염소진액 액기스 흙염소즙 효능 30포",
      "productName": "한려담원 지리산 토종 흑염소진액 액기스 흙염소즙 효능 30포",
      "category": "food-other",
      "source": "딜바다 국내",
      "platform": "네이버",
      "price": 75000,
      "priceText": "75,000원",
      "shipping": "무배",
      "discount": 0,
      "createdAt": "2026-04-28T15:00:00.000Z",
      "deadlineAt": "",
      "deadlineText": "",
      "statusText": "",
      "expiresAt": "",
      "eventTags": [
        "식품"
      ],
      "sourceCategory": "식품/건강",
      "summary": "한려담원 지리산 토종 흑염소진액 액기스 흙염소즙 효능 30포 특가입니다. 네이버 기준 75,000원, 무배.",
      "summaryPoints": [
        "플랫폼: 네이버",
        "가격: 75,000원",
        "배송: 무배"
      ],
      "originalUrl": "https://www.dealbada.com/bbs/board.php?bo_table=deal_domestic&wr_id=569147&page=1",
      "purchaseUrl": "https://www.dealbada.com/bbs/link.php?bo_table=deal_domestic&wr_id=569147&no=1&page=1",
      "url": "https://www.dealbada.com/bbs/board.php?bo_table=deal_domestic&wr_id=569147&page=1"
    },
    {
      "id": 57,
      "title": "[알리] 가시없는 고등어순살 대(1L) 1봉(6팩) 700g~800g",
      "productName": "가시없는 고등어순살 대(1L) 1봉(6팩) 700g~800g",
      "category": "overseas",
      "source": "딜바다 국내",
      "platform": "알리",
      "price": 21854,
      "priceText": "21,854원",
      "shipping": "무료",
      "discount": 0,
      "createdAt": "2026-04-28T15:00:00.000Z",
      "deadlineAt": "",
      "deadlineText": "",
      "statusText": "",
      "expiresAt": "",
      "eventTags": [],
      "sourceCategory": "식품/건강",
      "summary": "가시없는 고등어순살 대(1L) 1봉(6팩) 700g~800g 특가입니다. 알리 기준 21,854원, 무료.",
      "summaryPoints": [
        "플랫폼: 알리",
        "가격: 21,854원",
        "배송: 무료"
      ],
      "originalUrl": "https://www.dealbada.com/bbs/board.php?bo_table=deal_domestic&wr_id=569146&page=1",
      "purchaseUrl": "https://www.dealbada.com/bbs/link.php?bo_table=deal_domestic&wr_id=569146&no=1&page=1",
      "url": "https://www.dealbada.com/bbs/board.php?bo_table=deal_domestic&wr_id=569146&page=1"
    },
    {
      "id": 58,
      "title": "[지마켓] 아이스 쿨러 500ml",
      "productName": "아이스 쿨러 500ml",
      "category": "festa",
      "source": "딜바다 국내",
      "platform": "지마켓",
      "price": 13810,
      "priceText": "13,810원",
      "shipping": "무료배송",
      "discount": 0,
      "createdAt": "2026-04-28T15:00:00.000Z",
      "deadlineAt": "",
      "deadlineText": "",
      "statusText": "",
      "expiresAt": "",
      "eventTags": [
        "할인페스타"
      ],
      "sourceCategory": "기타",
      "summary": "아이스 쿨러 500ml 특가입니다. 지마켓 기준 13,810원, 무료배송.",
      "summaryPoints": [
        "플랫폼: 지마켓",
        "가격: 13,810원",
        "배송: 무료배송"
      ],
      "originalUrl": "https://www.dealbada.com/bbs/board.php?bo_table=deal_domestic&wr_id=569145&page=1",
      "purchaseUrl": "https://www.dealbada.com/bbs/link.php?bo_table=deal_domestic&wr_id=569145&no=1&page=1",
      "url": "https://www.dealbada.com/bbs/board.php?bo_table=deal_domestic&wr_id=569145&page=1"
    },
    {
      "id": 59,
      "title": "[딜바다 국내] 아디다스 골프 아디파워 26 보아 스파이크리스 골프화",
      "productName": "아디다스 골프 아디파워 26 보아 스파이크리스 골프화",
      "category": "festa",
      "source": "딜바다 국내",
      "platform": "",
      "price": 146300,
      "priceText": "146,300원",
      "shipping": "무료",
      "discount": 0,
      "createdAt": "2026-04-28T15:00:00.000Z",
      "deadlineAt": "",
      "deadlineText": "",
      "statusText": "",
      "expiresAt": "",
      "eventTags": [
        "할인페스타"
      ],
      "sourceCategory": "의류/잡화",
      "summary": "아디다스 골프 아디파워 26 보아 스파이크리스 골프화 특가입니다. 146,300원, 무료.",
      "summaryPoints": [
        "가격: 146,300원",
        "배송: 무료"
      ],
      "originalUrl": "https://www.dealbada.com/bbs/board.php?bo_table=deal_domestic&wr_id=569144&page=1",
      "purchaseUrl": "https://www.dealbada.com/bbs/link.php?bo_table=deal_domestic&wr_id=569144&no=1&page=1",
      "url": "https://www.dealbada.com/bbs/board.php?bo_table=deal_domestic&wr_id=569144&page=1"
    },
    {
      "id": 60,
      "title": "[네이버] 린클 음식물처리기 프라임S 가정의달 라이브",
      "productName": "린클 음식물처리기 프라임S 가정의달 라이브",
      "category": "electronics",
      "source": "딜바다 국내",
      "platform": "네이버",
      "price": 638000,
      "priceText": "638,000원",
      "shipping": "무료",
      "discount": 0,
      "createdAt": "2026-04-28T15:00:00.000Z",
      "deadlineAt": "",
      "deadlineText": "",
      "statusText": "",
      "expiresAt": "",
      "eventTags": [
        "라이브특가"
      ],
      "sourceCategory": "가전",
      "summary": "린클 음식물처리기 프라임S 가정의달 라이브 특가입니다. 네이버 기준 638,000원, 무료.",
      "summaryPoints": [
        "플랫폼: 네이버",
        "가격: 638,000원",
        "배송: 무료"
      ],
      "originalUrl": "https://www.dealbada.com/bbs/board.php?bo_table=deal_domestic&wr_id=569143&page=1",
      "purchaseUrl": "https://www.dealbada.com/bbs/link.php?bo_table=deal_domestic&wr_id=569143&no=1&page=1",
      "url": "https://www.dealbada.com/bbs/board.php?bo_table=deal_domestic&wr_id=569143&page=1"
    },
    {
      "id": 61,
      "title": "[네이버] 도레이씨 안경닦이",
      "productName": "도레이씨 안경닦이",
      "category": "festa",
      "source": "딜바다 국내",
      "platform": "네이버",
      "price": 5340,
      "priceText": "5,340원",
      "shipping": "무료",
      "discount": 0,
      "createdAt": "2026-04-28T15:00:00.000Z",
      "deadlineAt": "",
      "deadlineText": "",
      "statusText": "",
      "expiresAt": "",
      "eventTags": [
        "할인페스타"
      ],
      "sourceCategory": "기타",
      "summary": "도레이씨 안경닦이 특가입니다. 네이버 기준 5,340원, 무료.",
      "summaryPoints": [
        "플랫폼: 네이버",
        "가격: 5,340원",
        "배송: 무료"
      ],
      "originalUrl": "https://www.dealbada.com/bbs/board.php?bo_table=deal_domestic&wr_id=569142&page=1",
      "purchaseUrl": "https://www.dealbada.com/bbs/link.php?bo_table=deal_domestic&wr_id=569142&no=1&page=1",
      "url": "https://www.dealbada.com/bbs/board.php?bo_table=deal_domestic&wr_id=569142&page=1"
    },
    {
      "id": 62,
      "title": "[네이버] 푸로포뮬라 가정의달 선물세트 타임딜 올리브오일 발사믹 애사비",
      "productName": "푸로포뮬라 가정의달 선물세트 타임딜 올리브오일 발사믹 애사비",
      "category": "food-other",
      "source": "딜바다 국내",
      "platform": "네이버",
      "price": 19300,
      "priceText": "19,300원",
      "shipping": "",
      "discount": 0,
      "createdAt": "2026-04-28T15:00:00.000Z",
      "deadlineAt": "",
      "deadlineText": "",
      "statusText": "",
      "expiresAt": "",
      "eventTags": [
        "식품"
      ],
      "sourceCategory": "식품/건강",
      "summary": "푸로포뮬라 가정의달 선물세트 타임딜 올리브오일 발사믹 애사비 특가입니다. 네이버 기준 19,300원.",
      "summaryPoints": [
        "플랫폼: 네이버",
        "가격: 19,300원"
      ],
      "originalUrl": "https://www.dealbada.com/bbs/board.php?bo_table=deal_domestic&wr_id=569141&page=1",
      "purchaseUrl": "https://www.dealbada.com/bbs/link.php?bo_table=deal_domestic&wr_id=569141&no=1&page=1",
      "url": "https://www.dealbada.com/bbs/board.php?bo_table=deal_domestic&wr_id=569141&page=1"
    },
    {
      "id": 63,
      "title": "[딜바다 국내] 전자동 커피머신 더 크레마 라떼",
      "productName": "전자동 커피머신 더 크레마 라떼",
      "category": "electronics",
      "source": "딜바다 국내",
      "platform": "",
      "price": 351900,
      "priceText": "351,900원",
      "shipping": "무료",
      "discount": 0,
      "createdAt": "2026-04-28T15:00:00.000Z",
      "deadlineAt": "",
      "deadlineText": "",
      "statusText": "",
      "expiresAt": "",
      "eventTags": [
        "커피"
      ],
      "sourceCategory": "가전",
      "summary": "전자동 커피머신 더 크레마 라떼 특가입니다. 351,900원, 무료.",
      "summaryPoints": [
        "가격: 351,900원",
        "배송: 무료"
      ],
      "originalUrl": "https://www.dealbada.com/bbs/board.php?bo_table=deal_domestic&wr_id=569140&page=1",
      "purchaseUrl": "https://www.dealbada.com/bbs/link.php?bo_table=deal_domestic&wr_id=569140&no=1&page=1",
      "url": "https://www.dealbada.com/bbs/board.php?bo_table=deal_domestic&wr_id=569140&page=1"
    },
    {
      "id": 64,
      "title": "[네이버] 필립스 라떼고 5000시리즈 전자동 에스프레소 커피머신 EP5547/93 + 아크릴 컵 선반",
      "productName": "필립스 라떼고 5000시리즈 전자동 에스프레소 커피머신 EP5547/93 + 아크릴 컵 선반",
      "category": "electronics",
      "source": "딜바다 국내",
      "platform": "네이버",
      "price": 864800,
      "priceText": "864,800원",
      "shipping": "무료",
      "discount": 0,
      "createdAt": "2026-04-28T15:00:00.000Z",
      "deadlineAt": "",
      "deadlineText": "",
      "statusText": "",
      "expiresAt": "",
      "eventTags": [
        "커피"
      ],
      "sourceCategory": "가전",
      "summary": "필립스 라떼고 5000시리즈 전자동 에스프레소 커피머신 EP5547/93 + 아크릴 컵 선반 특가입니다. 네이버 기준 864,800원, 무료.",
      "summaryPoints": [
        "플랫폼: 네이버",
        "가격: 864,800원",
        "배송: 무료"
      ],
      "originalUrl": "https://www.dealbada.com/bbs/board.php?bo_table=deal_domestic&wr_id=569139&page=1",
      "purchaseUrl": "https://www.dealbada.com/bbs/link.php?bo_table=deal_domestic&wr_id=569139&no=1&page=1",
      "url": "https://www.dealbada.com/bbs/board.php?bo_table=deal_domestic&wr_id=569139&page=1"
    },
    {
      "id": 65,
      "title": "[지마켓] 관절보호 부상방지 슬개골 무릎보호대 1+1",
      "productName": "관절보호 부상방지 슬개골 무릎보호대 1+1",
      "category": "festa",
      "source": "딜바다 국내",
      "platform": "지마켓",
      "price": 8500,
      "priceText": "8,500원",
      "shipping": "무배",
      "discount": 0,
      "createdAt": "2026-04-28T15:00:00.000Z",
      "deadlineAt": "",
      "deadlineText": "",
      "statusText": "",
      "expiresAt": "",
      "eventTags": [
        "할인페스타"
      ],
      "sourceCategory": "기타",
      "summary": "관절보호 부상방지 슬개골 무릎보호대 1+1 특가입니다. 지마켓 기준 8,500원, 무배.",
      "summaryPoints": [
        "플랫폼: 지마켓",
        "가격: 8,500원",
        "배송: 무배"
      ],
      "originalUrl": "https://www.dealbada.com/bbs/board.php?bo_table=deal_domestic&wr_id=569138&page=1",
      "purchaseUrl": "https://www.dealbada.com/bbs/link.php?bo_table=deal_domestic&wr_id=569138&no=1&page=1",
      "url": "https://www.dealbada.com/bbs/board.php?bo_table=deal_domestic&wr_id=569138&page=1"
    },
    {
      "id": 66,
      "title": "[지마켓] 향기 스팀 온열 수면안대 40매",
      "productName": "향기 스팀 온열 수면안대 40매",
      "category": "game",
      "source": "딜바다 국내",
      "platform": "지마켓",
      "price": 10560,
      "priceText": "10,560원",
      "shipping": "무료",
      "discount": 0,
      "createdAt": "2026-04-28T15:00:00.000Z",
      "deadlineAt": "",
      "deadlineText": "",
      "statusText": "",
      "expiresAt": "",
      "eventTags": [],
      "sourceCategory": "기타",
      "summary": "향기 스팀 온열 수면안대 40매 특가입니다. 지마켓 기준 10,560원, 무료.",
      "summaryPoints": [
        "플랫폼: 지마켓",
        "가격: 10,560원",
        "배송: 무료"
      ],
      "originalUrl": "https://www.dealbada.com/bbs/board.php?bo_table=deal_domestic&wr_id=569137&page=2",
      "purchaseUrl": "https://www.dealbada.com/bbs/link.php?bo_table=deal_domestic&wr_id=569137&no=1&page=1",
      "url": "https://www.dealbada.com/bbs/board.php?bo_table=deal_domestic&wr_id=569137&page=2"
    },
    {
      "id": 67,
      "title": "[쿠팡] LG 그램 15ZD90S-GX5VK",
      "productName": "LG 그램 15ZD90S-GX5VK",
      "category": "festa",
      "source": "딜바다 국내",
      "platform": "쿠팡",
      "price": 1189300,
      "priceText": "1,189,300원",
      "shipping": "무료",
      "discount": 0,
      "createdAt": "2026-04-28T15:00:00.000Z",
      "deadlineAt": "",
      "deadlineText": "",
      "statusText": "",
      "expiresAt": "",
      "eventTags": [
        "할인페스타"
      ],
      "sourceCategory": "컴퓨터",
      "summary": "LG 그램 15ZD90S-GX5VK 특가입니다. 쿠팡 기준 1,189,300원, 무료.",
      "summaryPoints": [
        "플랫폼: 쿠팡",
        "가격: 1,189,300원",
        "배송: 무료"
      ],
      "originalUrl": "https://www.dealbada.com/bbs/board.php?bo_table=deal_domestic&wr_id=569136&page=2",
      "purchaseUrl": "https://www.dealbada.com/bbs/link.php?bo_table=deal_domestic&wr_id=569136&no=1&page=1",
      "url": "https://www.dealbada.com/bbs/board.php?bo_table=deal_domestic&wr_id=569136&page=2"
    },
    {
      "id": 68,
      "title": "[딜바다 국내] 오특 에이페 스칼프 부스팅 앰플 대용량",
      "productName": "[올리브영] 오특 에이페 스칼프 부스팅 앰플 대용량",
      "category": "kitchen",
      "source": "딜바다 국내",
      "platform": "",
      "price": 25900,
      "priceText": "25900원",
      "shipping": "무배",
      "discount": 0,
      "createdAt": "2026-04-28T15:00:00.000Z",
      "deadlineAt": "",
      "deadlineText": "",
      "statusText": "",
      "expiresAt": "",
      "eventTags": [],
      "sourceCategory": "화장품",
      "summary": "[올리브영] 오특 에이페 스칼프 부스팅 앰플 대용량 특가입니다. 25900원, 무배.",
      "summaryPoints": [
        "가격: 25900원",
        "배송: 무배"
      ],
      "originalUrl": "https://www.dealbada.com/bbs/board.php?bo_table=deal_domestic&wr_id=569135&page=2",
      "purchaseUrl": "https://www.dealbada.com/bbs/link.php?bo_table=deal_domestic&wr_id=569135&no=1&page=1",
      "url": "https://www.dealbada.com/bbs/board.php?bo_table=deal_domestic&wr_id=569135&page=2"
    },
    {
      "id": 69,
      "title": "[알리] 다기능 슬링백",
      "productName": "다기능 슬링백",
      "category": "overseas",
      "source": "딜바다 국내",
      "platform": "알리",
      "price": 21500,
      "priceText": "21,500원",
      "shipping": "무료",
      "discount": 0,
      "createdAt": "2026-04-28T15:00:00.000Z",
      "deadlineAt": "",
      "deadlineText": "",
      "statusText": "",
      "expiresAt": "",
      "eventTags": [],
      "sourceCategory": "의류/잡화",
      "summary": "다기능 슬링백 특가입니다. 알리 기준 21,500원, 무료.",
      "summaryPoints": [
        "플랫폼: 알리",
        "가격: 21,500원",
        "배송: 무료"
      ],
      "originalUrl": "https://www.dealbada.com/bbs/board.php?bo_table=deal_domestic&wr_id=569134&page=2",
      "purchaseUrl": "https://www.dealbada.com/bbs/link.php?bo_table=deal_domestic&wr_id=569134&no=1&page=1",
      "url": "https://www.dealbada.com/bbs/board.php?bo_table=deal_domestic&wr_id=569134&page=2"
    },
    {
      "id": 70,
      "title": "[지마켓] 독일산 맥주효모 비오틴 플러스 검정콩 6개월분",
      "productName": "독일산 맥주효모 비오틴 플러스 검정콩 6개월분",
      "category": "food-other",
      "source": "딜바다 국내",
      "platform": "지마켓",
      "price": 12900,
      "priceText": "12,900원",
      "shipping": "무료배송",
      "discount": 0,
      "createdAt": "2026-04-28T15:00:00.000Z",
      "deadlineAt": "",
      "deadlineText": "",
      "statusText": "",
      "expiresAt": "",
      "eventTags": [
        "식품"
      ],
      "sourceCategory": "식품/건강",
      "summary": "독일산 맥주효모 비오틴 플러스 검정콩 6개월분 특가입니다. 지마켓 기준 12,900원, 무료배송.",
      "summaryPoints": [
        "플랫폼: 지마켓",
        "가격: 12,900원",
        "배송: 무료배송"
      ],
      "originalUrl": "https://www.dealbada.com/bbs/board.php?bo_table=deal_domestic&wr_id=569133&page=2",
      "purchaseUrl": "https://www.dealbada.com/bbs/link.php?bo_table=deal_domestic&wr_id=569133&no=1&page=1",
      "url": "https://www.dealbada.com/bbs/board.php?bo_table=deal_domestic&wr_id=569133&page=2"
    },
    {
      "id": 71,
      "title": "[개드립] 선착순 5000원 할인쿠폰 0원",
      "productName": "선착순 5000원 할인쿠폰 0원",
      "category": "food-other",
      "source": "개드립",
      "platform": "",
      "price": 5000,
      "priceText": "5000원",
      "shipping": "무료",
      "discount": 0,
      "createdAt": "2026-04-28T06:09:07.343Z",
      "deadlineAt": "",
      "deadlineText": "",
      "statusText": "선착순",
      "expiresAt": "",
      "eventTags": [
        "쿠폰"
      ],
      "sourceCategory": "식품",
      "summary": "선착순 5000원 할인쿠폰 0원 특가입니다. 5000원, 무료. 조건: 선착순 5000.",
      "summaryPoints": [
        "가격: 5000원",
        "배송: 무료",
        "조건: 선착순 5000"
      ],
      "originalUrl": "https://www.dogdrip.net/hotdeal/698861248?sort_index=popular&page=1",
      "purchaseUrl": "",
      "url": "https://www.dogdrip.net/hotdeal/698861248?sort_index=popular&page=1"
    },
    {
      "id": 72,
      "title": "[amazon] Netgear MK73-100NAR Nighthawk Dual-Band AX3000 3-Pack 3Gbps WiFi 6 Mesh System Router and 2...",
      "productName": "Netgear MK73-100NAR Nighthawk Dual-Band AX3000 3-Pack 3Gbps WiFi 6 Mesh System Router and 2...",
      "category": "overseas",
      "source": "해외뽐뿌",
      "platform": "amazon",
      "price": 0,
      "priceText": "",
      "shipping": "",
      "discount": 0,
      "createdAt": "2026-04-27T15:00:00.000Z",
      "deadlineAt": "",
      "deadlineText": "",
      "statusText": "",
      "expiresAt": "",
      "eventTags": [],
      "sourceCategory": "",
      "summary": "Netgear MK73-100NAR Nighthawk Dual-Band AX3000 3-Pack 3Gbps WiFi 6 Mesh System Router and 2... 특가입니다. amazon 기준.",
      "summaryPoints": [
        "플랫폼: amazon"
      ],
      "originalUrl": "https://www.ppomppu.co.kr/zboard/view.php?id=ppomppu4&page=1&divpage=23&no=126875",
      "purchaseUrl": "https://s.ppomppu.co.kr/?idno=ppomppu4_126875&target=aHR0cHM6Ly93d3cuYW1hem9uLmNvbS9OZXRnZWFyLU1LNzMtMTAwTkFSLU5pZ2h0aGF3ay1EdWFsLUJhbmQtU2F0ZWxsaXRlcy9kcC9CMEMzSk5GWjVSL3JlZj1zcl8xXzY/Y3JpZD0yS0dGSjAxTEZKNkVZJmRpYj1leUoySWpvaU1TSjkuWWVMSGhLbG1LanRlMlE3YTNmaWY3bmZobFVkLUtNNFF2R2Y5bXFkMU93VkN3TEZtYThwLTNuZXpNcVpaZ1FtOVZFOU1rUUpyVW5FQUY4cC12eGFlOGFaSXBhRXFTazE2MW5aeGY5TC0taERNUzB4eUZiWnNkN2Z4&encode=on",
      "url": "https://www.ppomppu.co.kr/zboard/view.php?id=ppomppu4&page=1&divpage=23&no=126875"
    },
    {
      "id": 73,
      "title": "[네이버] 쿠쿠 큐브 음식물처리기",
      "productName": "쿠쿠 큐브 음식물처리기",
      "category": "electronics",
      "source": "딜바다 국내",
      "platform": "네이버",
      "price": 370280,
      "priceText": "370,280원",
      "shipping": "무료",
      "discount": 0,
      "createdAt": "2026-04-27T15:00:00.000Z",
      "deadlineAt": "",
      "deadlineText": "",
      "statusText": "",
      "expiresAt": "",
      "eventTags": [],
      "sourceCategory": "가전",
      "summary": "쿠쿠 큐브 음식물처리기 특가입니다. 네이버 기준 370,280원, 무료.",
      "summaryPoints": [
        "플랫폼: 네이버",
        "가격: 370,280원",
        "배송: 무료"
      ],
      "originalUrl": "https://www.dealbada.com/bbs/board.php?bo_table=deal_domestic&wr_id=569132&page=2",
      "purchaseUrl": "https://www.dealbada.com/bbs/link.php?bo_table=deal_domestic&wr_id=569132&no=1&page=1",
      "url": "https://www.dealbada.com/bbs/board.php?bo_table=deal_domestic&wr_id=569132&page=2"
    },
    {
      "id": 74,
      "title": "[네이버] 비타도스D 비타민D3 5000IU 고함량 DSM 스위스산 고용량 30캡슐 1개",
      "productName": "비타도스D 비타민D3 5000IU 고함량 DSM 스위스산 고용량 30캡슐 1개",
      "category": "food-other",
      "source": "딜바다 국내",
      "platform": "네이버",
      "price": 2920,
      "priceText": "2,920원",
      "shipping": "무료",
      "discount": 0,
      "createdAt": "2026-04-27T15:00:00.000Z",
      "deadlineAt": "",
      "deadlineText": "",
      "statusText": "",
      "expiresAt": "",
      "eventTags": [
        "식품"
      ],
      "sourceCategory": "식품/건강",
      "summary": "비타도스D 비타민D3 5000IU 고함량 DSM 스위스산 고용량 30캡슐 1개 특가입니다. 네이버 기준 2,920원, 무료.",
      "summaryPoints": [
        "플랫폼: 네이버",
        "가격: 2,920원",
        "배송: 무료"
      ],
      "originalUrl": "https://www.dealbada.com/bbs/board.php?bo_table=deal_domestic&wr_id=569131&page=2",
      "purchaseUrl": "https://www.dealbada.com/bbs/link.php?bo_table=deal_domestic&wr_id=569131&no=1&page=1",
      "url": "https://www.dealbada.com/bbs/board.php?bo_table=deal_domestic&wr_id=569131&page=2"
    },
    {
      "id": 75,
      "title": "[11번가] RAZER 키시 V2 USB C 모바일 게임패드",
      "productName": "RAZER 키시 V2 USB C 모바일 게임패드",
      "category": "game",
      "source": "딜바다 국내",
      "platform": "11번가",
      "price": 79000,
      "priceText": "79,000원",
      "shipping": "무료",
      "discount": 0,
      "createdAt": "2026-04-27T15:00:00.000Z",
      "deadlineAt": "",
      "deadlineText": "",
      "statusText": "",
      "expiresAt": "",
      "eventTags": [],
      "sourceCategory": "디지털",
      "summary": "RAZER 키시 V2 USB C 모바일 게임패드 특가입니다. 11번가 기준 79,000원, 무료.",
      "summaryPoints": [
        "플랫폼: 11번가",
        "가격: 79,000원",
        "배송: 무료"
      ],
      "originalUrl": "https://www.dealbada.com/bbs/board.php?bo_table=deal_domestic&wr_id=569130&page=2",
      "purchaseUrl": "https://www.dealbada.com/bbs/link.php?bo_table=deal_domestic&wr_id=569130&no=1&page=1",
      "url": "https://www.dealbada.com/bbs/board.php?bo_table=deal_domestic&wr_id=569130&page=2"
    },
    {
      "id": 76,
      "title": "[딜바다 국내] 모두맑음 볼륨 탈모샴푸 480ml",
      "productName": "[첫구매특가/정가70,000원] 모두맑음 볼륨 탈모샴푸 480ml",
      "category": "festa",
      "source": "딜바다 국내",
      "platform": "",
      "price": 100,
      "priceText": "100원",
      "shipping": "",
      "discount": 0,
      "createdAt": "2026-04-27T15:00:00.000Z",
      "deadlineAt": "",
      "deadlineText": "",
      "statusText": "",
      "expiresAt": "",
      "eventTags": [
        "할인페스타"
      ],
      "sourceCategory": "화장품",
      "summary": "[첫구매특가/정가70,000원] 모두맑음 볼륨 탈모샴푸 480ml 특가입니다. 100원.",
      "summaryPoints": [
        "가격: 100원"
      ],
      "originalUrl": "https://www.dealbada.com/bbs/board.php?bo_table=deal_domestic&wr_id=569129&page=2",
      "purchaseUrl": "https://www.dealbada.com/bbs/link.php?bo_table=deal_domestic&wr_id=569129&no=1&page=1",
      "url": "https://www.dealbada.com/bbs/board.php?bo_table=deal_domestic&wr_id=569129&page=2"
    },
    {
      "id": 77,
      "title": "[딜바다 국내] 스킨케어 3종세트 (토너+앰플+크림)",
      "productName": "스킨케어 3종세트 (토너+앰플+크림)",
      "category": "festa",
      "source": "딜바다 국내",
      "platform": "",
      "price": 9690,
      "priceText": "9,690원",
      "shipping": "무료",
      "discount": 0,
      "createdAt": "2026-04-27T15:00:00.000Z",
      "deadlineAt": "",
      "deadlineText": "",
      "statusText": "",
      "expiresAt": "",
      "eventTags": [
        "할인페스타"
      ],
      "sourceCategory": "화장품",
      "summary": "스킨케어 3종세트 (토너+앰플+크림) 특가입니다. 9,690원, 무료.",
      "summaryPoints": [
        "가격: 9,690원",
        "배송: 무료"
      ],
      "originalUrl": "https://www.dealbada.com/bbs/board.php?bo_table=deal_domestic&wr_id=569128&page=2",
      "purchaseUrl": "https://www.dealbada.com/bbs/link.php?bo_table=deal_domestic&wr_id=569128&no=1&page=1",
      "url": "https://www.dealbada.com/bbs/board.php?bo_table=deal_domestic&wr_id=569128&page=2"
    },
    {
      "id": 78,
      "title": "[딜바다 국내] 프란츠) 줄기세포배양액 10%앰플 4EA 패밀리 세일 모음전 19,900원",
      "productName": "프란츠) 줄기세포배양액 10%앰플 4EA 패밀리 세일 모음전 19,900원",
      "category": "festa",
      "source": "딜바다 국내",
      "platform": "",
      "price": 19900,
      "priceText": "19,900원",
      "shipping": "",
      "discount": 10,
      "createdAt": "2026-04-27T15:00:00.000Z",
      "deadlineAt": "",
      "deadlineText": "",
      "statusText": "",
      "expiresAt": "",
      "eventTags": [
        "할인페스타"
      ],
      "sourceCategory": "기타",
      "summary": "프란츠) 줄기세포배양액 10%앰플 4EA 패밀리 세일 모음전 19,900원 특가입니다. 19,900원.",
      "summaryPoints": [
        "가격: 19,900원"
      ],
      "originalUrl": "https://www.dealbada.com/bbs/board.php?bo_table=deal_domestic&wr_id=569127&page=2",
      "purchaseUrl": "https://www.dealbada.com/bbs/link.php?bo_table=deal_domestic&wr_id=569127&no=1&page=1",
      "url": "https://www.dealbada.com/bbs/board.php?bo_table=deal_domestic&wr_id=569127&page=2"
    },
    {
      "id": 79,
      "title": "[딜바다 국내] 너겟 47 요금제 체감가",
      "productName": "너겟 47 요금제 체감가",
      "category": "frozen",
      "source": "딜바다 국내",
      "platform": "",
      "price": 27000,
      "priceText": "27,000원",
      "shipping": "무료",
      "discount": 0,
      "createdAt": "2026-04-27T15:00:00.000Z",
      "deadlineAt": "",
      "deadlineText": "",
      "statusText": "",
      "expiresAt": "",
      "eventTags": [
        "식품"
      ],
      "sourceCategory": "기타",
      "summary": "너겟 47 요금제 체감가 특가입니다. 27,000원, 무료.",
      "summaryPoints": [
        "가격: 27,000원",
        "배송: 무료"
      ],
      "originalUrl": "https://www.dealbada.com/bbs/board.php?bo_table=deal_domestic&wr_id=569126&page=2",
      "purchaseUrl": "https://www.dealbada.com/bbs/link.php?bo_table=deal_domestic&wr_id=569126&no=1&page=1",
      "url": "https://www.dealbada.com/bbs/board.php?bo_table=deal_domestic&wr_id=569126&page=2"
    },
    {
      "id": 80,
      "title": "[딜바다 국내] 종근당건강 난각막NEM 90일/관절연골 뮤코다당단백 콘드로이친120일",
      "productName": "종근당건강 난각막NEM 90일/관절연골 뮤코다당단백 콘드로이친120일",
      "category": "food-other",
      "source": "딜바다 국내",
      "platform": "",
      "price": 66800,
      "priceText": "66,800원",
      "shipping": "무료",
      "discount": 0,
      "createdAt": "2026-04-27T15:00:00.000Z",
      "deadlineAt": "",
      "deadlineText": "",
      "statusText": "",
      "expiresAt": "",
      "eventTags": [
        "식품"
      ],
      "sourceCategory": "식품/건강",
      "summary": "종근당건강 난각막NEM 90일/관절연골 뮤코다당단백 콘드로이친120일 특가입니다. 66,800원, 무료.",
      "summaryPoints": [
        "가격: 66,800원",
        "배송: 무료"
      ],
      "originalUrl": "https://www.dealbada.com/bbs/board.php?bo_table=deal_domestic&wr_id=569125&page=2",
      "purchaseUrl": "https://www.dealbada.com/bbs/link.php?bo_table=deal_domestic&wr_id=569125&no=1&page=1",
      "url": "https://www.dealbada.com/bbs/board.php?bo_table=deal_domestic&wr_id=569125&page=2"
    },
    {
      "id": 81,
      "title": "[11번가] 부사 사과 4kg 가정용 소과 25~35과",
      "productName": "부사 사과 4kg 가정용 소과 25~35과",
      "category": "produce",
      "source": "딜바다 국내",
      "platform": "11번가",
      "price": 11990,
      "priceText": "11,990원",
      "shipping": "무료",
      "discount": 0,
      "createdAt": "2026-04-27T15:00:00.000Z",
      "deadlineAt": "",
      "deadlineText": "",
      "statusText": "",
      "expiresAt": "",
      "eventTags": [
        "식품"
      ],
      "sourceCategory": "식품/건강",
      "summary": "부사 사과 4kg 가정용 소과 25~35과 특가입니다. 11번가 기준 11,990원, 무료.",
      "summaryPoints": [
        "플랫폼: 11번가",
        "가격: 11,990원",
        "배송: 무료"
      ],
      "originalUrl": "https://www.dealbada.com/bbs/board.php?bo_table=deal_domestic&wr_id=569124&page=2",
      "purchaseUrl": "https://www.dealbada.com/bbs/link.php?bo_table=deal_domestic&wr_id=569124&no=1&page=1",
      "url": "https://www.dealbada.com/bbs/board.php?bo_table=deal_domestic&wr_id=569124&page=2"
    },
    {
      "id": 82,
      "title": "[지마켓] 나비 스톰 에어 서큘레이터 자동회전 선풍기",
      "productName": "나비 스톰 에어 서큘레이터 자동회전 선풍기",
      "category": "electronics",
      "source": "딜바다 국내",
      "platform": "지마켓",
      "price": 22020,
      "priceText": "22,020원",
      "shipping": "무배",
      "discount": 0,
      "createdAt": "2026-04-27T15:00:00.000Z",
      "deadlineAt": "",
      "deadlineText": "",
      "statusText": "",
      "expiresAt": "",
      "eventTags": [],
      "sourceCategory": "가전",
      "summary": "나비 스톰 에어 서큘레이터 자동회전 선풍기 특가입니다. 지마켓 기준 22,020원, 무배.",
      "summaryPoints": [
        "플랫폼: 지마켓",
        "가격: 22,020원",
        "배송: 무배"
      ],
      "originalUrl": "https://www.dealbada.com/bbs/board.php?bo_table=deal_domestic&wr_id=569123&page=2",
      "purchaseUrl": "https://www.dealbada.com/bbs/link.php?bo_table=deal_domestic&wr_id=569123&no=1&page=1",
      "url": "https://www.dealbada.com/bbs/board.php?bo_table=deal_domestic&wr_id=569123&page=2"
    },
    {
      "id": 83,
      "title": "[알리] 누보 숄더백 컬러매칭",
      "productName": "누보 숄더백 컬러매칭",
      "category": "overseas",
      "source": "딜바다 해외",
      "platform": "알리",
      "price": 41200,
      "priceText": "41,200원",
      "shipping": "무료",
      "discount": 0,
      "createdAt": "2026-04-27T15:00:00.000Z",
      "deadlineAt": "",
      "deadlineText": "",
      "statusText": "",
      "expiresAt": "",
      "eventTags": [],
      "sourceCategory": "의류/잡화",
      "summary": "누보 숄더백 컬러매칭 특가입니다. 알리 기준 41,200원, 무료.",
      "summaryPoints": [
        "플랫폼: 알리",
        "가격: 41,200원",
        "배송: 무료"
      ],
      "originalUrl": "https://www.dealbada.com/bbs/board.php?bo_table=deal_oversea&wr_id=307967&page=1",
      "purchaseUrl": "https://www.dealbada.com/bbs/link.php?bo_table=deal_oversea&wr_id=307967&no=1&page=1",
      "url": "https://www.dealbada.com/bbs/board.php?bo_table=deal_oversea&wr_id=307967&page=1"
    },
    {
      "id": 84,
      "title": "[해외뽐뿌] 와플땅콩빵 100개입",
      "productName": "와플땅콩빵 100개입",
      "category": "overseas",
      "source": "해외뽐뿌",
      "platform": "",
      "price": 6407,
      "priceText": "6,407원",
      "shipping": "",
      "discount": 0,
      "createdAt": "2026-04-26T15:00:00.000Z",
      "deadlineAt": "",
      "deadlineText": "",
      "statusText": "",
      "expiresAt": "",
      "eventTags": [],
      "sourceCategory": "",
      "summary": "와플땅콩빵 100개입 특가입니다. 6,407원.",
      "summaryPoints": [
        "가격: 6,407원"
      ],
      "originalUrl": "https://www.ppomppu.co.kr/zboard/view.php?id=ppomppu4&page=1&divpage=23&no=126874",
      "purchaseUrl": "https://s.ppomppu.co.kr/?idno=ppomppu4_126874&target=aHR0cHM6Ly93d3cudGVtdS5jb20vZ29vZHMuaHRtbD9fYmdfZnM9MSZnb29kc19pZD02MDUxNjg2NDA4MjM4OTQ=&encode=on",
      "url": "https://www.ppomppu.co.kr/zboard/view.php?id=ppomppu4&page=1&divpage=23&no=126874"
    },
    {
      "id": 85,
      "title": "[해외뽐뿌] 런팔콘5",
      "productName": "런팔콘5",
      "category": "overseas",
      "source": "해외뽐뿌",
      "platform": "",
      "price": 0,
      "priceText": "",
      "shipping": "",
      "discount": 0,
      "createdAt": "2026-04-26T15:00:00.000Z",
      "deadlineAt": "",
      "deadlineText": "",
      "statusText": "",
      "expiresAt": "",
      "eventTags": [],
      "sourceCategory": "",
      "summary": "런팔콘5 특가입니다.",
      "summaryPoints": [],
      "originalUrl": "https://www.ppomppu.co.kr/zboard/view.php?id=ppomppu4&page=1&divpage=23&no=126871",
      "purchaseUrl": "https://s.ppomppu.co.kr/?idno=ppomppu4_126871&target=aHR0cHM6Ly93d3cuYWRpZGFzLmNvbS91cy9ydW5mYWxjb24tNS13aWRlLXJ1bm5pbmctc2hvZXMvSUUwNTUyLmh0bWw/Zm9yY2VTZWxTaXplPUlFMDU1Ml82MjA=&encode=on",
      "url": "https://www.ppomppu.co.kr/zboard/view.php?id=ppomppu4&page=1&divpage=23&no=126871"
    },
    {
      "id": 86,
      "title": "[알리] 스포츠 고글 선글라스",
      "productName": "스포츠 고글 선글라스",
      "category": "overseas",
      "source": "딜바다 해외",
      "platform": "알리",
      "price": 17450,
      "priceText": "17,450원",
      "shipping": "무료",
      "discount": 0,
      "createdAt": "2026-04-26T15:00:00.000Z",
      "deadlineAt": "",
      "deadlineText": "",
      "statusText": "",
      "expiresAt": "",
      "eventTags": [],
      "sourceCategory": "의류/잡화",
      "summary": "스포츠 고글 선글라스 특가입니다. 알리 기준 17,450원, 무료.",
      "summaryPoints": [
        "플랫폼: 알리",
        "가격: 17,450원",
        "배송: 무료"
      ],
      "originalUrl": "https://www.dealbada.com/bbs/board.php?bo_table=deal_oversea&wr_id=307966&page=1",
      "purchaseUrl": "https://www.dealbada.com/bbs/link.php?bo_table=deal_oversea&wr_id=307966&no=1&page=1",
      "url": "https://www.dealbada.com/bbs/board.php?bo_table=deal_oversea&wr_id=307966&page=1"
    },
    {
      "id": 87,
      "title": "[EBAY] HP EliteBook 845 G9: 14\" WUXGA - AMD Ryzen 5- 32GB|256GB (certified-refurbished) ($399.99/무료...",
      "productName": "HP EliteBook 845 G9: 14\" WUXGA - AMD Ryzen 5- 32GB|256GB (certified-refurbished) ($399.99/무료...",
      "category": "overseas",
      "source": "해외뽐뿌",
      "platform": "EBAY",
      "price": 0,
      "priceText": "",
      "shipping": "무료",
      "discount": 0,
      "createdAt": "2026-04-24T15:00:00.000Z",
      "deadlineAt": "",
      "deadlineText": "",
      "statusText": "",
      "expiresAt": "",
      "eventTags": [],
      "sourceCategory": "",
      "summary": "HP EliteBook 845 G9: 14\" WUXGA - AMD Ryzen 5- 32GB|256GB (certified-refurbished) ($399.99/무료... 특가입니다. EBAY 기준 무료.",
      "summaryPoints": [
        "플랫폼: EBAY",
        "배송: 무료"
      ],
      "originalUrl": "https://www.ppomppu.co.kr/zboard/view.php?id=ppomppu4&page=1&divpage=23&no=126869",
      "purchaseUrl": "https://s.ppomppu.co.kr/?idno=ppomppu4_126869&target=aHR0cHM6Ly93d3cuZWJheS5jb20vaXRtLzE2ODMyNzU4NzI2OD9fc2t3PUhQK0VsaXRlQm9vays4NDUrRzklM0ErMTQlMjIrV1VYR0ErLStBTUQrUnl6ZW4rNS0rMzJHQiU3QzI1NkdCKy0rV2luKzExK1BybyZpdG1tZXRhPTAxS1EwVzFRSjZRWTFLMldDUk4xUlhDUkpBJmhhc2g9aXRlbTI3MzExYjI1YzQlM0FnJTNBeXhzQUFlU3cxcmxwNjduMyZpdG0=&encode=on",
      "url": "https://www.ppomppu.co.kr/zboard/view.php?id=ppomppu4&page=1&divpage=23&no=126869"
    },
    {
      "id": 88,
      "title": "[알리익스프레스] 4월 베이비 페어 정보 안내",
      "productName": "4월 베이비 페어 정보 안내",
      "category": "overseas",
      "source": "알리뽐뿌",
      "platform": "알리익스프레스",
      "price": 0,
      "priceText": "",
      "shipping": "",
      "discount": 0,
      "createdAt": "2026-04-23T15:00:00.000Z",
      "deadlineAt": "",
      "deadlineText": "",
      "statusText": "",
      "expiresAt": "",
      "eventTags": [],
      "sourceCategory": "",
      "summary": "4월 베이비 페어 정보 안내 특가입니다. 알리익스프레스 기준.",
      "summaryPoints": [
        "플랫폼: 알리익스프레스"
      ],
      "originalUrl": "https://www.ppomppu.co.kr/zboard/view.php?id=ppomppu8&page=1&divpage=15&no=86931",
      "purchaseUrl": "",
      "url": "https://www.ppomppu.co.kr/zboard/view.php?id=ppomppu8&page=1&divpage=15&no=86931"
    },
    {
      "id": 89,
      "title": "[알리] 아크릴 파충류 사육 상자 가열 패드가있는 겨울 인큐베이터",
      "productName": "아크릴 파충류 사육 상자 가열 패드가있는 겨울 인큐베이터",
      "category": "overseas",
      "source": "딜바다 해외",
      "platform": "알리",
      "price": 33971,
      "priceText": "33,971원",
      "shipping": "무료",
      "discount": 0,
      "createdAt": "2026-04-21T15:00:00.000Z",
      "deadlineAt": "",
      "deadlineText": "",
      "statusText": "",
      "expiresAt": "",
      "eventTags": [],
      "sourceCategory": "가전",
      "summary": "아크릴 파충류 사육 상자 가열 패드가있는 겨울 인큐베이터 특가입니다. 알리 기준 33,971원, 무료.",
      "summaryPoints": [
        "플랫폼: 알리",
        "가격: 33,971원",
        "배송: 무료"
      ],
      "originalUrl": "https://www.dealbada.com/bbs/board.php?bo_table=deal_oversea&wr_id=307965&page=1",
      "purchaseUrl": "https://www.dealbada.com/bbs/link.php?bo_table=deal_oversea&wr_id=307965&no=1&page=1",
      "url": "https://www.dealbada.com/bbs/board.php?bo_table=deal_oversea&wr_id=307965&page=1"
    },
    {
      "id": 90,
      "title": "[해외뽐뿌] 오스프리 울트라라이트 스터프 팩",
      "productName": "오스프리 울트라라이트 스터프 팩",
      "category": "overseas",
      "source": "해외뽐뿌",
      "platform": "",
      "price": 0,
      "priceText": "",
      "shipping": "무배",
      "discount": 0,
      "createdAt": "2026-04-19T15:00:00.000Z",
      "deadlineAt": "",
      "deadlineText": "",
      "statusText": "",
      "expiresAt": "",
      "eventTags": [],
      "sourceCategory": "",
      "summary": "오스프리 울트라라이트 스터프 팩 특가입니다. 무배.",
      "summaryPoints": [
        "배송: 무배"
      ],
      "originalUrl": "https://www.ppomppu.co.kr/zboard/view.php?id=ppomppu4&page=1&divpage=23&no=126868",
      "purchaseUrl": "https://s.ppomppu.co.kr/?idno=ppomppu4_126868&target=aHR0cHM6Ly93d3cuMTFzdC5jby5rci9wcm9kdWN0cy9wYS83MDkwMTk2NDMw&encode=on",
      "url": "https://www.ppomppu.co.kr/zboard/view.php?id=ppomppu4&page=1&divpage=23&no=126868"
    },
    {
      "id": 91,
      "title": "[알리] 캐주얼 멀티 포켓 메신저 가방",
      "productName": "캐주얼 멀티 포켓 메신저 가방",
      "category": "overseas",
      "source": "딜바다 해외",
      "platform": "알리",
      "price": 17200,
      "priceText": "17,200원",
      "shipping": "무료",
      "discount": 0,
      "createdAt": "2026-04-19T15:00:00.000Z",
      "deadlineAt": "",
      "deadlineText": "",
      "statusText": "",
      "expiresAt": "",
      "eventTags": [],
      "sourceCategory": "의류/잡화",
      "summary": "캐주얼 멀티 포켓 메신저 가방 특가입니다. 알리 기준 17,200원, 무료.",
      "summaryPoints": [
        "플랫폼: 알리",
        "가격: 17,200원",
        "배송: 무료"
      ],
      "originalUrl": "https://www.dealbada.com/bbs/board.php?bo_table=deal_oversea&wr_id=307964&page=1",
      "purchaseUrl": "https://www.dealbada.com/bbs/link.php?bo_table=deal_oversea&wr_id=307964&no=1&page=1",
      "url": "https://www.dealbada.com/bbs/board.php?bo_table=deal_oversea&wr_id=307964&page=1"
    },
    {
      "id": 92,
      "title": "[해외뽐뿌] Logitech MX2S [조건부 Free] / 미국내 조건부 무료)",
      "productName": "Logitech MX2S [조건부 Free] / 미국내 조건부 무료)",
      "category": "overseas",
      "source": "해외뽐뿌",
      "platform": "",
      "price": 0,
      "priceText": "",
      "shipping": "무료",
      "discount": 0,
      "createdAt": "2026-04-17T15:00:00.000Z",
      "deadlineAt": "",
      "deadlineText": "",
      "statusText": "",
      "expiresAt": "",
      "eventTags": [],
      "sourceCategory": "",
      "summary": "Logitech MX2S [조건부 Free] / 미국내 조건부 무료) 특가입니다. 무료.",
      "summaryPoints": [
        "배송: 무료"
      ],
      "originalUrl": "https://www.ppomppu.co.kr/zboard/view.php?id=ppomppu4&page=1&divpage=23&no=126867",
      "purchaseUrl": "https://s.ppomppu.co.kr/?idno=ppomppu4_126867&target=aHR0cHM6Ly93d3cuYmVzdGJ1eS5jb20=&encode=on",
      "url": "https://www.ppomppu.co.kr/zboard/view.php?id=ppomppu4&page=1&divpage=23&no=126867"
    },
    {
      "id": 93,
      "title": "[알리] M2 헤드업 디스플레이 GPS HUD 디지털 속도계 플러그 앤 플레이",
      "productName": "M2 헤드업 디스플레이 GPS HUD 디지털 속도계 플러그 앤 플레이",
      "category": "overseas",
      "source": "딜바다 해외",
      "platform": "알리",
      "price": 9200,
      "priceText": "9,200원",
      "shipping": "무료배송",
      "discount": 0,
      "createdAt": "2026-04-16T15:00:00.000Z",
      "deadlineAt": "",
      "deadlineText": "",
      "statusText": "",
      "expiresAt": "",
      "eventTags": [],
      "sourceCategory": "디지털",
      "summary": "M2 헤드업 디스플레이 GPS HUD 디지털 속도계 플러그 앤 플레이 특가입니다. 알리 기준 9,200원, 무료배송.",
      "summaryPoints": [
        "플랫폼: 알리",
        "가격: 9,200원",
        "배송: 무료배송"
      ],
      "originalUrl": "https://www.dealbada.com/bbs/board.php?bo_table=deal_oversea&wr_id=307963&page=1",
      "purchaseUrl": "https://www.dealbada.com/bbs/link.php?bo_table=deal_oversea&wr_id=307963&no=1&page=1",
      "url": "https://www.dealbada.com/bbs/board.php?bo_table=deal_oversea&wr_id=307963&page=1"
    },
    {
      "id": 94,
      "title": "[알리] USB 3포트 220V멀티탭",
      "productName": "USB 3포트 220V멀티탭",
      "category": "overseas",
      "source": "딜바다 해외",
      "platform": "알리",
      "price": 7321,
      "priceText": "7,321원",
      "shipping": "무료",
      "discount": 0,
      "createdAt": "2026-04-16T15:00:00.000Z",
      "deadlineAt": "",
      "deadlineText": "",
      "statusText": "",
      "expiresAt": "",
      "eventTags": [],
      "sourceCategory": "가전",
      "summary": "USB 3포트 220V멀티탭 특가입니다. 알리 기준 7,321원, 무료.",
      "summaryPoints": [
        "플랫폼: 알리",
        "가격: 7,321원",
        "배송: 무료"
      ],
      "originalUrl": "https://www.dealbada.com/bbs/board.php?bo_table=deal_oversea&wr_id=307962&page=1",
      "purchaseUrl": "https://www.dealbada.com/bbs/link.php?bo_table=deal_oversea&wr_id=307962&no=1&page=1",
      "url": "https://www.dealbada.com/bbs/board.php?bo_table=deal_oversea&wr_id=307962&page=1"
    }
  ]
}
